<?xml version="1.0" encoding="UTF-8" standalone="yes" ?>
<root>
    <facilities id="1" type="1" level="2" fullfill="360" step="10" fund="38000" material="10" exploit="20" item_type_1="2000002" item_num_1="3" item_type_2="2000007" item_num_2="3" item_type_3="2000012" item_num_3="3" item_type_4="2000017" item_num_4="3" item_type_5="2000202" item_num_5="3" item_type_6="2000207" item_num_6="3" item_type_7="2000212" item_num_7="3" item_type_8="2000217" item_num_8="3" item_type_9="3110001" item_num_9="1" item_type_10="3110002" item_num_10="1" item_type_11="3110003" item_num_11="1" item_type_12="3110004" item_num_12="1" item_type_13="2430083" item_num_13="10" item_type_14="2430104" item_num_14="10" item_type_15="2430123" item_num_15="10" item_type_16="2430144" item_num_16="10" item_type_17="2430164" item_num_17="10" item_type_18="2430183" item_num_18="10" item_type_19="2430204" item_num_19="10" item_type_20="2430224" item_num_20="10" />
    <facilities id="2" type="1" level="3" fullfill="600" step="10" fund="68000" material="20" exploit="20" item_type_1="2000002" item_num_1="3" item_type_2="2000007" item_num_2="3" item_type_3="2000012" item_num_3="3" item_type_4="2000017" item_num_4="3" item_type_5="2000202" item_num_5="3" item_type_6="2000207" item_num_6="3" item_type_7="2000212" item_num_7="3" item_type_8="2000217" item_num_8="3" item_type_9="3110001" item_num_9="1" item_type_10="3110002" item_num_10="1" item_type_11="3110003" item_num_11="1" item_type_12="3110004" item_num_12="1" item_type_13="2430104" item_num_13="10" item_type_14="2430123" item_num_14="10" item_type_15="2430144" item_num_15="10" item_type_16="2430164" item_num_16="10" item_type_17="2430183" item_num_17="10" item_type_18="2430204" item_num_18="10" item_type_19="2430224" item_num_19="10" item_type_20="2430244" item_num_20="10" />
    <facilities id="3" type="1" level="4" fullfill="1000" step="10" fund="88000" material="30" exploit="20" item_type_1="2000003" item_num_1="1" item_type_2="2000008" item_num_2="1" item_type_3="2000013" item_num_3="1" item_type_4="2000018" item_num_4="1" item_type_5="2000023" item_num_5="1" item_type_6="2000203" item_num_6="1" item_type_7="2000208" item_num_7="1" item_type_8="2000213" item_num_8="1" item_type_9="2000218" item_num_9="1" item_type_10="2000223" item_num_10="1" item_type_11="3110005" item_num_11="1" item_type_12="3110006" item_num_12="1" item_type_13="3110007" item_num_13="1" item_type_14="3110008" item_num_14="1" item_type_15="3110009" item_num_15="1" item_type_16="3110010" item_num_16="1" item_type_17="2430244" item_num_17="10" item_type_18="2430263" item_num_18="10" item_type_19="2430284" item_num_19="10" item_type_20="2430304" item_num_20="10" />
    <facilities id="4" type="1" level="5" fullfill="1600" step="10" fund="108000" material="40" exploit="20" item_type_1="2000003" item_num_1="1" item_type_2="2000008" item_num_2="1" item_type_3="2000013" item_num_3="1" item_type_4="2000018" item_num_4="1" item_type_5="2000023" item_num_5="1" item_type_6="2000203" item_num_6="1" item_type_7="2000208" item_num_7="1" item_type_8="2000213" item_num_8="1" item_type_9="2000218" item_num_9="1" item_type_10="2000223" item_num_10="1" item_type_11="3110005" item_num_11="1" item_type_12="3110006" item_num_12="1" item_type_13="3110007" item_num_13="1" item_type_14="3110008" item_num_14="1" item_type_15="3110009" item_num_15="1" item_type_16="3110010" item_num_16="1" item_type_17="2430244" item_num_17="10" item_type_18="2430263" item_num_18="10" item_type_19="2430284" item_num_19="10" item_type_20="2430304" item_num_20="10" />
    <facilities id="10" type="2" level="1" fullfill="100" step="10" fund="8000" material="5" exploit="20" item_type_1="2430083" item_num_1="10" item_type_2="2430104" item_num_2="10" item_type_3="2430123" item_num_3="10" item_type_4="2430144" item_num_4="10" item_type_5="2430164" item_num_5="10" item_type_6="2430183" item_num_6="10" />
    <facilities id="11" type="2" level="2" fullfill="180" step="10" fund="18000" material="5" exploit="20" item_type_1="3110001" item_num_1="1" item_type_2="3110002" item_num_2="1" item_type_3="3110003" item_num_3="1" item_type_4="3110004" item_num_4="1" item_type_5="2430083" item_num_5="10" item_type_6="2430104" item_num_6="10" item_type_7="2430123" item_num_7="10" item_type_8="2430144" item_num_8="10" item_type_9="2430164" item_num_9="10" item_type_10="2430183" item_num_10="10" item_type_11="2430204" item_num_11="10" item_type_12="2430224" item_num_12="10" item_type_13="2430244" item_num_13="10" />
    <facilities id="12" type="2" level="3" fullfill="300" step="10" fund="38000" material="10" exploit="20" item_type_1="3110001" item_num_1="1" item_type_2="3110002" item_num_2="1" item_type_3="3110003" item_num_3="1" item_type_4="3110004" item_num_4="1" item_type_5="2430083" item_num_5="10" item_type_6="2430104" item_num_6="10" item_type_7="2430123" item_num_7="10" item_type_8="2430144" item_num_8="10" item_type_9="2430164" item_num_9="10" item_type_10="2430183" item_num_10="10" item_type_11="2430204" item_num_11="10" item_type_12="2430224" item_num_12="10" item_type_13="2430244" item_num_13="10" />
    <facilities id="13" type="2" level="4" fullfill="500" step="10" fund="58000" material="15" exploit="20" item_type_1="3110005" item_num_1="1" item_type_2="3110006" item_num_2="1" item_type_3="3110007" item_num_3="1" item_type_4="3110008" item_num_4="1" item_type_5="3110009" item_num_5="1" item_type_6="3110010" item_num_6="1" item_type_7="2430083" item_num_7="10" item_type_8="2430104" item_num_8="10" item_type_9="2430123" item_num_9="10" item_type_10="2430144" item_num_10="10" item_type_11="2430164" item_num_11="10" item_type_12="2430183" item_num_12="10" item_type_13="2430204" item_num_13="10" item_type_14="2430224" item_num_14="10" item_type_15="2430244" item_num_15="10" item_type_16="2430263" item_num_16="10" item_type_17="2430284" item_num_17="10" item_type_18="2430304" item_num_18="10" />
    <facilities id="14" type="2" level="5" fullfill="800" step="10" fund="88000" material="20" exploit="20" item_type_1="3110005" item_num_1="1" item_type_2="3110006" item_num_2="1" item_type_3="3110007" item_num_3="1" item_type_4="3110008" item_num_4="1" item_type_5="3110009" item_num_5="1" item_type_6="3110010" item_num_6="1" item_type_7="2430083" item_num_7="10" item_type_8="2430104" item_num_8="10" item_type_9="2430123" item_num_9="10" item_type_10="2430144" item_num_10="10" item_type_11="2430164" item_num_11="10" item_type_12="2430183" item_num_12="10" item_type_13="2430204" item_num_13="10" item_type_14="2430224" item_num_14="10" item_type_15="2430244" item_num_15="10" item_type_16="2430263" item_num_16="10" item_type_17="2430284" item_num_17="10" item_type_18="2430304" item_num_18="10" />
    <facilities id="20" type="3" level="1" fullfill="100" step="10" fund="8000" material="5" exploit="20" item_type_1="2430083" item_num_1="10" item_type_2="2430104" item_num_2="10" item_type_3="2430123" item_num_3="10" item_type_4="2430144" item_num_4="10" item_type_5="2430164" item_num_5="10" item_type_6="2430183" item_num_6="10" />
    <facilities id="21" type="3" level="2" fullfill="180" step="10" fund="18000" material="5" exploit="20" item_type_1="3110001" item_num_1="1" item_type_2="3110002" item_num_2="1" item_type_3="3110003" item_num_3="1" item_type_4="3110004" item_num_4="1" item_type_5="2430083" item_num_5="10" item_type_6="2430104" item_num_6="10" item_type_7="2430123" item_num_7="10" item_type_8="2430144" item_num_8="10" item_type_9="2430164" item_num_9="10" item_type_10="2430183" item_num_10="10" item_type_11="2430204" item_num_11="10" item_type_12="2430224" item_num_12="10" item_type_13="2430244" item_num_13="10" />
    <facilities id="22" type="3" level="3" fullfill="300" step="10" fund="38000" material="10" exploit="20" item_type_1="3110001" item_num_1="1" item_type_2="3110002" item_num_2="1" item_type_3="3110003" item_num_3="1" item_type_4="3110004" item_num_4="1" item_type_5="2430083" item_num_5="10" item_type_6="2430104" item_num_6="10" item_type_7="2430123" item_num_7="10" item_type_8="2430144" item_num_8="10" item_type_9="2430164" item_num_9="10" item_type_10="2430183" item_num_10="10" item_type_11="2430204" item_num_11="10" item_type_12="2430224" item_num_12="10" item_type_13="2430244" item_num_13="10" />
    <facilities id="23" type="3" level="4" fullfill="500" step="10" fund="58000" material="15" exploit="20" item_type_1="3110005" item_num_1="1" item_type_2="3110006" item_num_2="1" item_type_3="3110007" item_num_3="1" item_type_4="3110008" item_num_4="1" item_type_5="3110009" item_num_5="1" item_type_6="3110010" item_num_6="1" item_type_7="2430083" item_num_7="10" item_type_8="2430104" item_num_8="10" item_type_9="2430123" item_num_9="10" item_type_10="2430144" item_num_10="10" item_type_11="2430164" item_num_11="10" item_type_12="2430183" item_num_12="10" item_type_13="2430204" item_num_13="10" item_type_14="2430224" item_num_14="10" item_type_15="2430244" item_num_15="10" item_type_16="2430263" item_num_16="10" item_type_17="2430284" item_num_17="10" item_type_18="2430304" item_num_18="10" />
    <facilities id="24" type="3" level="5" fullfill="800" step="10" fund="88000" material="20" exploit="20" item_type_1="3110005" item_num_1="1" item_type_2="3110006" item_num_2="1" item_type_3="3110007" item_num_3="1" item_type_4="3110008" item_num_4="1" item_type_5="3110009" item_num_5="1" item_type_6="3110010" item_num_6="1" item_type_7="2430083" item_num_7="10" item_type_8="2430104" item_num_8="10" item_type_9="2430123" item_num_9="10" item_type_10="2430144" item_num_10="10" item_type_11="2430164" item_num_11="10" item_type_12="2430183" item_num_12="10" item_type_13="2430204" item_num_13="10" item_type_14="2430224" item_num_14="10" item_type_15="2430244" item_num_15="10" item_type_16="2430263" item_num_16="10" item_type_17="2430284" item_num_17="10" item_type_18="2430304" item_num_18="10" />
    <facilities id="30" type="4" level="1" fullfill="200" step="10" fund="8000" material="5" exploit="20" item_type_1="2430083" item_num_1="10" item_type_2="2430104" item_num_2="10" item_type_3="2430123" item_num_3="10" item_type_4="2430144" item_num_4="10" item_type_5="2430164" item_num_5="10" item_type_6="2430183" item_num_6="10" />
    <facilities id="31" type="4" level="2" fullfill="360" step="10" fund="18000" material="5" exploit="20" item_type_1="3110001" item_num_1="1" item_type_2="3110002" item_num_2="1" item_type_3="3110003" item_num_3="1" item_type_4="3110004" item_num_4="1" item_type_5="2430083" item_num_5="10" item_type_6="2430104" item_num_6="10" item_type_7="2430123" item_num_7="10" item_type_8="2430144" item_num_8="10" item_type_9="2430164" item_num_9="10" item_type_10="2430183" item_num_10="10" item_type_11="2430204" item_num_11="10" item_type_12="2430224" item_num_12="10" item_type_13="2430244" item_num_13="10" />
    <facilities id="32" type="4" level="3" fullfill="600" step="10" fund="38000" material="10" exploit="20" item_type_1="3110001" item_num_1="1" item_type_2="3110002" item_num_2="1" item_type_3="3110003" item_num_3="1" item_type_4="3110004" item_num_4="1" item_type_5="2430083" item_num_5="10" item_type_6="2430104" item_num_6="10" item_type_7="2430123" item_num_7="10" item_type_8="2430144" item_num_8="10" item_type_9="2430164" item_num_9="10" item_type_10="2430183" item_num_10="10" item_type_11="2430204" item_num_11="10" item_type_12="2430224" item_num_12="10" item_type_13="2430244" item_num_13="10" />
    <facilities id="33" type="4" level="4" fullfill="1000" step="10" fund="58000" material="15" exploit="20" item_type_1="3110005" item_num_1="1" item_type_2="3110006" item_num_2="1" item_type_3="3110007" item_num_3="1" item_type_4="3110008" item_num_4="1" item_type_5="3110009" item_num_5="1" item_type_6="3110010" item_num_6="1" item_type_7="2430083" item_num_7="10" item_type_8="2430104" item_num_8="10" item_type_9="2430123" item_num_9="10" item_type_10="2430144" item_num_10="10" item_type_11="2430164" item_num_11="10" item_type_12="2430183" item_num_12="10" item_type_13="2430204" item_num_13="10" item_type_14="2430224" item_num_14="10" item_type_15="2430244" item_num_15="10" item_type_16="2430263" item_num_16="10" item_type_17="2430284" item_num_17="10" item_type_18="2430304" item_num_18="10" />
    <facilities id="34" type="4" level="5" fullfill="1600" step="10" fund="88000" material="20" exploit="20" item_type_1="3110005" item_num_1="1" item_type_2="3110006" item_num_2="1" item_type_3="3110007" item_num_3="1" item_type_4="3110008" item_num_4="1" item_type_5="3110009" item_num_5="1" item_type_6="3110010" item_num_6="1" item_type_7="2430083" item_num_7="10" item_type_8="2430104" item_num_8="10" item_type_9="2430123" item_num_9="10" item_type_10="2430144" item_num_10="10" item_type_11="2430164" item_num_11="10" item_type_12="2430183" item_num_12="10" item_type_13="2430204" item_num_13="10" item_type_14="2430224" item_num_14="10" item_type_15="2430244" item_num_15="10" item_type_16="2430263" item_num_16="10" item_type_17="2430284" item_num_17="10" item_type_18="2430304" item_num_18="10" />
</root>
