<?xml version="1.0" encoding="UTF-8" standalone="yes" ?>
<root>
    <printing_proto id="1" level="1" att="8" val="500" costitemid="6000220" progress="10" rate="10000" cost="10000" item_cost="0" />
    <printing_proto id="2" level="1" att="10" val="500" costitemid="6000220" progress="10" rate="10000" cost="10000" item_cost="0" />
    <printing_proto id="3" level="1" att="13" val="100" costitemid="6000220" progress="10" rate="10000" cost="10000" item_cost="0" />
    <printing_proto id="4" level="1" att="15" val="100" costitemid="6000220" progress="10" rate="10000" cost="10000" item_cost="0" />
    <printing_proto id="5" level="1" att="0" val="10" costitemid="6000220" progress="10" rate="10000" cost="10000" item_cost="0" />
    <printing_proto id="6" level="1" att="1" val="10" costitemid="6000220" progress="10" rate="10000" cost="10000" item_cost="0" />
    <printing_proto id="7" level="1" att="2" val="10" costitemid="6000220" progress="10" rate="10000" cost="10000" item_cost="0" />
    <printing_proto id="8" level="1" att="3" val="10" costitemid="6000220" progress="10" rate="10000" cost="10000" item_cost="0" />
    <printing_proto id="9" level="1" att="4" val="10" costitemid="6000220" progress="10" rate="10000" cost="10000" item_cost="0" />
    <printing_proto id="10" level="1" att="5" val="10" costitemid="6000220" progress="10" rate="10000" cost="10000" item_cost="0" />
    <printing_proto id="11" level="2" att="8" val="700" costitemid="6000220" progress="30" rate="8000" cost="30000" item_cost="0" />
    <printing_proto id="12" level="2" att="10" val="700" costitemid="6000220" progress="30" rate="8000" cost="30000" item_cost="0" />
    <printing_proto id="13" level="2" att="13" val="150" costitemid="6000220" progress="30" rate="8000" cost="30000" item_cost="0" />
    <printing_proto id="14" level="2" att="15" val="150" costitemid="6000220" progress="30" rate="8000" cost="30000" item_cost="0" />
    <printing_proto id="15" level="2" att="16" val="250" costitemid="6000220" progress="30" rate="8000" cost="30000" item_cost="0" />
    <printing_proto id="16" level="2" att="17" val="250" costitemid="6000220" progress="30" rate="8000" cost="30000" item_cost="0" />
    <printing_proto id="17" level="2" att="0" val="13" costitemid="6000220" progress="30" rate="8000" cost="30000" item_cost="0" />
    <printing_proto id="18" level="2" att="1" val="13" costitemid="6000220" progress="30" rate="8000" cost="30000" item_cost="0" />
    <printing_proto id="19" level="2" att="2" val="13" costitemid="6000220" progress="30" rate="8000" cost="30000" item_cost="0" />
    <printing_proto id="20" level="2" att="3" val="13" costitemid="6000220" progress="30" rate="8000" cost="30000" item_cost="0" />
    <printing_proto id="21" level="2" att="4" val="13" costitemid="6000220" progress="30" rate="8000" cost="30000" item_cost="0" />
    <printing_proto id="22" level="2" att="5" val="13" costitemid="6000220" progress="30" rate="8000" cost="30000" item_cost="0" />
    <printing_proto id="23" level="3" att="8" val="1000" costitemid="6000220" progress="50" rate="6000" cost="50000" item_cost="1" />
    <printing_proto id="24" level="3" att="10" val="1000" costitemid="6000220" progress="50" rate="6000" cost="50000" item_cost="1" />
    <printing_proto id="25" level="3" att="13" val="200" costitemid="6000220" progress="50" rate="6000" cost="50000" item_cost="1" />
    <printing_proto id="26" level="3" att="15" val="200" costitemid="6000220" progress="50" rate="6000" cost="50000" item_cost="1" />
    <printing_proto id="27" level="3" att="12" val="100" costitemid="6000220" progress="50" rate="6000" cost="50000" item_cost="1" />
    <printing_proto id="28" level="3" att="14" val="100" costitemid="6000220" progress="50" rate="6000" cost="50000" item_cost="1" />
    <printing_proto id="29" level="3" att="16" val="300" costitemid="6000220" progress="50" rate="6000" cost="50000" item_cost="1" />
    <printing_proto id="30" level="3" att="17" val="300" costitemid="6000220" progress="50" rate="6000" cost="50000" item_cost="1" />
    <printing_proto id="31" level="3" att="0" val="18" costitemid="6000220" progress="50" rate="6000" cost="50000" item_cost="1" />
    <printing_proto id="32" level="3" att="1" val="18" costitemid="6000220" progress="50" rate="6000" cost="50000" item_cost="1" />
    <printing_proto id="33" level="3" att="2" val="18" costitemid="6000220" progress="50" rate="6000" cost="50000" item_cost="1" />
    <printing_proto id="34" level="3" att="3" val="18" costitemid="6000220" progress="50" rate="6000" cost="50000" item_cost="1" />
    <printing_proto id="35" level="3" att="4" val="18" costitemid="6000220" progress="50" rate="6000" cost="50000" item_cost="1" />
    <printing_proto id="36" level="3" att="5" val="18" costitemid="6000220" progress="50" rate="6000" cost="50000" item_cost="1" />
    <printing_proto id="37" level="4" att="8" val="1500" costitemid="6000220" progress="80" rate="4000" cost="80000" item_cost="2" />
    <printing_proto id="38" level="4" att="10" val="1500" costitemid="6000220" progress="80" rate="4000" cost="80000" item_cost="2" />
    <printing_proto id="39" level="4" att="13" val="280" costitemid="6000220" progress="80" rate="4000" cost="80000" item_cost="2" />
    <printing_proto id="40" level="4" att="15" val="280" costitemid="6000220" progress="80" rate="4000" cost="80000" item_cost="2" />
    <printing_proto id="41" level="4" att="12" val="200" costitemid="6000220" progress="80" rate="4000" cost="80000" item_cost="2" />
    <printing_proto id="42" level="4" att="14" val="200" costitemid="6000220" progress="80" rate="4000" cost="80000" item_cost="2" />
    <printing_proto id="43" level="4" att="16" val="375" costitemid="6000220" progress="80" rate="4000" cost="80000" item_cost="2" />
    <printing_proto id="44" level="4" att="17" val="375" costitemid="6000220" progress="80" rate="4000" cost="80000" item_cost="2" />
    <printing_proto id="45" level="4" att="0" val="22" costitemid="6000220" progress="80" rate="4000" cost="80000" item_cost="2" />
    <printing_proto id="46" level="4" att="1" val="22" costitemid="6000220" progress="80" rate="4000" cost="80000" item_cost="2" />
    <printing_proto id="47" level="4" att="2" val="22" costitemid="6000220" progress="80" rate="4000" cost="80000" item_cost="2" />
    <printing_proto id="48" level="4" att="3" val="22" costitemid="6000220" progress="80" rate="4000" cost="80000" item_cost="2" />
    <printing_proto id="49" level="4" att="4" val="22" costitemid="6000220" progress="80" rate="4000" cost="80000" item_cost="2" />
    <printing_proto id="50" level="4" att="5" val="22" costitemid="6000220" progress="80" rate="4000" cost="80000" item_cost="2" />
    <printing_proto id="51" level="5" att="8" val="2000" costitemid="6000220" progress="100" rate="2000" cost="100000" item_cost="5" />
    <printing_proto id="52" level="5" att="10" val="2000" costitemid="6000220" progress="100" rate="2000" cost="100000" item_cost="5" />
    <printing_proto id="53" level="5" att="13" val="400" costitemid="6000220" progress="100" rate="2000" cost="100000" item_cost="5" />
    <printing_proto id="54" level="5" att="15" val="400" costitemid="6000220" progress="100" rate="2000" cost="100000" item_cost="5" />
    <printing_proto id="55" level="5" att="12" val="320" costitemid="6000220" progress="100" rate="2000" cost="100000" item_cost="5" />
    <printing_proto id="56" level="5" att="14" val="320" costitemid="6000220" progress="100" rate="2000" cost="100000" item_cost="5" />
    <printing_proto id="57" level="5" att="16" val="475" costitemid="6000220" progress="100" rate="2000" cost="100000" item_cost="5" />
    <printing_proto id="58" level="5" att="17" val="475" costitemid="6000220" progress="100" rate="2000" cost="100000" item_cost="5" />
    <printing_proto id="59" level="5" att="0" val="30" costitemid="6000220" progress="100" rate="2000" cost="100000" item_cost="5" />
    <printing_proto id="60" level="5" att="1" val="30" costitemid="6000220" progress="100" rate="2000" cost="100000" item_cost="5" />
    <printing_proto id="61" level="5" att="2" val="30" costitemid="6000220" progress="100" rate="2000" cost="100000" item_cost="5" />
    <printing_proto id="62" level="5" att="3" val="30" costitemid="6000220" progress="100" rate="2000" cost="100000" item_cost="5" />
    <printing_proto id="63" level="5" att="4" val="30" costitemid="6000220" progress="100" rate="2000" cost="100000" item_cost="5" />
    <printing_proto id="64" level="5" att="5" val="30" costitemid="6000220" progress="100" rate="2000" cost="100000" item_cost="5" />
    <printing_proto id="65" level="5" att="33" val="35" costitemid="6000220" progress="100" rate="2000" cost="100000" item_cost="5" />
    <printing_proto id="66" level="5" att="34" val="20" costitemid="6000220" progress="100" rate="2000" cost="100000" item_cost="5" />
    <printing_proto id="67" level="5" att="44" val="40" costitemid="6000220" progress="100" rate="2000" cost="100000" item_cost="5" />
    <printing_proto id="68" level="5" att="45" val="40" costitemid="6000220" progress="100" rate="2000" cost="100000" item_cost="5" />
    <printing_proto id="69" level="5" att="46" val="20" costitemid="6000220" progress="100" rate="2000" cost="100000" item_cost="5" />
    <printing_proto id="70" level="6" att="8" val="3000" costitemid="6000220" progress="130" rate="1300" cost="130000" item_cost="12" />
    <printing_proto id="71" level="6" att="10" val="3000" costitemid="6000220" progress="130" rate="1300" cost="130000" item_cost="12" />
    <printing_proto id="72" level="6" att="13" val="550" costitemid="6000220" progress="130" rate="1300" cost="130000" item_cost="12" />
    <printing_proto id="73" level="6" att="15" val="550" costitemid="6000220" progress="130" rate="1300" cost="130000" item_cost="12" />
    <printing_proto id="74" level="6" att="12" val="450" costitemid="6000220" progress="130" rate="1300" cost="130000" item_cost="12" />
    <printing_proto id="75" level="6" att="14" val="450" costitemid="6000220" progress="130" rate="1300" cost="130000" item_cost="12" />
    <printing_proto id="76" level="6" att="16" val="600" costitemid="6000220" progress="130" rate="1300" cost="130000" item_cost="12" />
    <printing_proto id="77" level="6" att="17" val="600" costitemid="6000220" progress="130" rate="1300" cost="130000" item_cost="12" />
    <printing_proto id="78" level="6" att="0" val="40" costitemid="6000220" progress="130" rate="1300" cost="130000" item_cost="12" />
    <printing_proto id="79" level="6" att="1" val="40" costitemid="6000220" progress="130" rate="1300" cost="130000" item_cost="12" />
    <printing_proto id="80" level="6" att="2" val="40" costitemid="6000220" progress="130" rate="1300" cost="130000" item_cost="12" />
    <printing_proto id="81" level="6" att="3" val="40" costitemid="6000220" progress="130" rate="1300" cost="130000" item_cost="12" />
    <printing_proto id="82" level="6" att="4" val="40" costitemid="6000220" progress="130" rate="1300" cost="130000" item_cost="12" />
    <printing_proto id="83" level="6" att="5" val="40" costitemid="6000220" progress="130" rate="1300" cost="130000" item_cost="12" />
    <printing_proto id="84" level="6" att="33" val="45" costitemid="6000220" progress="130" rate="1300" cost="130000" item_cost="12" />
    <printing_proto id="85" level="6" att="34" val="30" costitemid="6000220" progress="130" rate="1300" cost="130000" item_cost="12" />
    <printing_proto id="86" level="6" att="44" val="50" costitemid="6000220" progress="130" rate="1300" cost="130000" item_cost="12" />
    <printing_proto id="87" level="6" att="45" val="50" costitemid="6000220" progress="130" rate="1300" cost="130000" item_cost="12" />
    <printing_proto id="88" level="6" att="46" val="30" costitemid="6000220" progress="130" rate="1300" cost="130000" item_cost="12" />
    <printing_proto id="89" level="6" att="102" val="1170" costitemid="6000220" progress="130" rate="1300" cost="130000" item_cost="12" />
    <printing_proto id="90" level="7" att="8" val="5000" costitemid="6000220" progress="150" rate="1000" cost="150000" item_cost="22" />
    <printing_proto id="91" level="7" att="10" val="5000" costitemid="6000220" progress="150" rate="1000" cost="150000" item_cost="22" />
    <printing_proto id="92" level="7" att="13" val="700" costitemid="6000220" progress="150" rate="1000" cost="150000" item_cost="22" />
    <printing_proto id="93" level="7" att="15" val="700" costitemid="6000220" progress="150" rate="1000" cost="150000" item_cost="22" />
    <printing_proto id="94" level="7" att="12" val="600" costitemid="6000220" progress="150" rate="1000" cost="150000" item_cost="22" />
    <printing_proto id="95" level="7" att="14" val="600" costitemid="6000220" progress="150" rate="1000" cost="150000" item_cost="22" />
    <printing_proto id="96" level="7" att="16" val="750" costitemid="6000220" progress="150" rate="1000" cost="150000" item_cost="22" />
    <printing_proto id="97" level="7" att="17" val="750" costitemid="6000220" progress="150" rate="1000" cost="150000" item_cost="22" />
    <printing_proto id="98" level="7" att="0" val="55" costitemid="6000220" progress="150" rate="1000" cost="150000" item_cost="22" />
    <printing_proto id="99" level="7" att="1" val="55" costitemid="6000220" progress="150" rate="1000" cost="150000" item_cost="22" />
    <printing_proto id="100" level="7" att="2" val="55" costitemid="6000220" progress="150" rate="1000" cost="150000" item_cost="22" />
    <printing_proto id="101" level="7" att="3" val="55" costitemid="6000220" progress="150" rate="1000" cost="150000" item_cost="22" />
    <printing_proto id="102" level="7" att="4" val="55" costitemid="6000220" progress="150" rate="1000" cost="150000" item_cost="22" />
    <printing_proto id="103" level="7" att="5" val="55" costitemid="6000220" progress="150" rate="1000" cost="150000" item_cost="22" />
    <printing_proto id="104" level="7" att="33" val="60" costitemid="6000220" progress="150" rate="1000" cost="150000" item_cost="22" />
    <printing_proto id="105" level="7" att="34" val="45" costitemid="6000220" progress="150" rate="1000" cost="150000" item_cost="22" />
    <printing_proto id="106" level="7" att="44" val="60" costitemid="6000220" progress="150" rate="1000" cost="150000" item_cost="22" />
    <printing_proto id="107" level="7" att="45" val="60" costitemid="6000220" progress="150" rate="1000" cost="150000" item_cost="22" />
    <printing_proto id="108" level="7" att="46" val="40" costitemid="6000220" progress="150" rate="1000" cost="150000" item_cost="22" />
    <printing_proto id="109" level="7" att="102" val="1500" costitemid="6000220" progress="150" rate="1000" cost="150000" item_cost="22" />
    <printing_proto id="110" level="7" att="103" val="1170" costitemid="6000220" progress="150" rate="1000" cost="150000" item_cost="22" />
</root>
