<?xml version="1.0" encoding="UTF-8" ?>
<desktop>
    <UIControl Name="guardwin" ClassName="CGUIWindow" Movable="yes" CanMoveOutOfFather="yes" LogicPos_x="728" LogicPos_y="306" Size_x="380" Size_y="185" PopupSound="window_popup">
        <UIControl Name="item" ClassName="CGUIPatch" MoveFather="yes" LogicPos_x="126" Size_x="128" Size_y="185" AlignOffset_x="126" Text="道具栏" Font="小白雅黑" FontHeight="20" FontWeight="800" TextRect_top="5" TextRect_right="128" TextRect_bottom="185" TextColor="0xFFFFF2A4" ShadeColor="0xFF290404" TextWriteAlpha="yes" TextAlign="CenterTop" PicColor="0xEEFFFFFF" AlphaWrite="Write" TopPicFileName="data\ui\pet\l-pet.bmp" TopPicRect_left="9" TopPicRect_right="18" TopPicRect_bottom="9" MidPicFileName="data\ui\pet\l-pet.bmp" MidPicRect_left="9" MidPicRect_top="9" MidPicRect_right="18" MidPicRect_bottom="18" DownPicFileName="data\ui\pet\l-pet.bmp" DownPicRect_left="9" DownPicRect_top="18" DownPicRect_right="18" DownPicRect_bottom="27" LeftPicFileName="data\ui\pet\l-pet.bmp" LeftPicRect_top="9" LeftPicRect_right="9" LeftPicRect_bottom="18" RightPicFileName="data\ui\pet\l-pet.bmp" RightPicRect_left="18" RightPicRect_top="9" RightPicRect_right="27" RightPicRect_bottom="18" LeftTopPicFileName="data\ui\pet\l-pet.bmp" LeftTopPicRect_right="9" LeftTopPicRect_bottom="9" RightTopPicFileName="data\ui\pet\l-pet.bmp" RightTopPicRect_left="18" RightTopPicRect_right="27" RightTopPicRect_bottom="9" LeftDownPicFileName="data\ui\pet\l-pet.bmp" LeftDownPicRect_top="18" LeftDownPicRect_right="9" LeftDownPicRect_bottom="27" RightDownPicFileName="data\ui\pet\l-pet.bmp" RightDownPicRect_left="18" RightDownPicRect_top="18" RightDownPicRect_right="27" RightDownPicRect_bottom="27">
            <UIControl Name="warehousebutt" ClassName="CGUIButton" LogicPos_x="7" LogicPos_y="5" Size_x="23" Size_y="22" Font="小三楷体" TextRect_right="128" TextRect_bottom="128" TextColor="0xFFFFF2A4" ShadeColor="0xFF290404" PicFileName="data\ui\common\l-common.bmp" PicRect_left="425" PicRect_top="68" PicRect_right="400" PicRect_bottom="91" PicColor="0xFFFFFFFF" AlphaWrite="Add" Tips="收起/展开仓库栏位" PushPicFileName="data\ui\common\l-common.bmp" PushPicRect_left="481" PushPicRect_top="68" PushPicRect_right="456" PushPicRect_bottom="91" PushPicColor="0xFFFFFFFF" PushTextColor="0xFFFFF2A4" PushShadeColor="0xFF290404" MovePicFileName="data\ui\common\l-common.bmp" MovePicRect_left="453" MovePicRect_top="68" MovePicRect_right="428" MovePicRect_bottom="91" MovePicColor="0xFFFFFFFF" MoveTextColor="0xFFFFF2A4" MoveShadeColor="0xFF290404" DisablePicFileName="data\ui\common\l-common.bmp" DisablePicRect_left="481" DisablePicRect_top="68" DisablePicRect_right="456" DisablePicRect_bottom="91" DisablePicColor="0xFF808080" DisableTextColor="0xFF808080" DisableShadeColor="0xFF290404" TopColor="0xFF000000" BottomColor="0xFFAFAFAF" />
            <UIControl Name="butt" ClassName="CGUIButton" LogicPos_x="96" LogicPos_y="5" Size_x="23" Size_y="22" Font="小三楷体" TextRect_right="25" TextRect_bottom="22" TextColor="0xFFFFF2A4" ShadeColor="0xFF290404" PicFileName="data\ui\common\l-common.bmp" PicRect_left="400" PicRect_top="68" PicRect_right="425" PicRect_bottom="91" PicColor="0xFFFFFFFF" AlphaWrite="Add" Tips="收起/展开积分信息" PushPicFileName="data\ui\common\l-common.bmp" PushPicRect_left="456" PushPicRect_top="68" PushPicRect_right="481" PushPicRect_bottom="91" PushPicColor="0xFFFFFFFF" PushTextColor="0xFFFFF2A4" PushShadeColor="0xFF290404" MovePicFileName="data\ui\common\l-common.bmp" MovePicRect_left="428" MovePicRect_top="68" MovePicRect_right="453" MovePicRect_bottom="91" MovePicColor="0xFFFFFFFF" MoveTextColor="0xFFFFF2A4" MoveShadeColor="0xFF290404" DisablePicFileName="data\ui\common\l-common.bmp" DisablePicColor="0xFFFFFFFF" DisableTextColor="0xFFFFF2A4" DisableShadeColor="0xFF290404" TopColor="0xFF000000" BottomColor="0xFFAFAFAF" />
            <UIControl Name="item0" ClassName="CGUIStatic" LogicPos_x="15" LogicPos_y="30" Size_x="44" Size_y="44" Font="小白雅黑" TextRect_right="44" TextRect_bottom="44" TextColor="0xFFFFF2A4" ShadeColor="0xFF290404" PicFileName="data\ui\common\l_icon.bmp" PicColor="0xFFFFFFFF" AlphaWrite="Add">
                <UIControl Name="icon" ClassName="CGUIStatic" LogicPos_x="4" LogicPos_y="4" Size_x="36" Size_y="36" Font="小白雅黑" FontHeight="15" TextRect_right="34" TextRect_bottom="36" TextColor="0xFFFFFFFF" ShadeColor="0xFF000000" TextWriteAlpha="yes" TextAlign="RightBottom" PicColor="0xFFFFFFFF" AlphaWrite="Add" />
            </UIControl>
            <UIControl Name="item1" ClassName="CGUIStatic" LogicPos_x="69" LogicPos_y="30" Size_x="44" Size_y="44" Font="小白雅黑" TextRect_right="44" TextRect_bottom="44" TextColor="0xFFFFF2A4" ShadeColor="0xFF290404" PicFileName="data\ui\common\l_icon.bmp" PicColor="0xFFFFFFFF" AlphaWrite="Add">
                <UIControl Name="icon" ClassName="CGUIStatic" LogicPos_x="4" LogicPos_y="4" Size_x="36" Size_y="36" Font="小白雅黑" FontHeight="15" TextRect_right="34" TextRect_bottom="36" TextColor="0xFFFFFFFF" ShadeColor="0xFF000000" TextWriteAlpha="yes" TextAlign="RightBottom" PicColor="0xFFFFFFFF" AlphaWrite="Add" />
            </UIControl>
            <UIControl Name="item2" ClassName="CGUIStatic" LogicPos_x="15" LogicPos_y="79" Size_x="44" Size_y="44" Font="小白雅黑" TextRect_right="44" TextRect_bottom="44" TextColor="0xFFFFF2A4" ShadeColor="0xFF290404" TextWriteAlpha="yes" PicFileName="data\ui\common\l_icon.bmp" PicColor="0xFFFFFFFF" AlphaWrite="Add">
                <UIControl Name="icon" ClassName="CGUIStatic" LogicPos_x="4" LogicPos_y="4" Size_x="36" Size_y="36" Font="小白雅黑" FontHeight="15" TextRect_right="34" TextRect_bottom="36" TextColor="0xFFFFFFFF" ShadeColor="0xFF000000" TextWriteAlpha="yes" TextAlign="RightBottom" PicColor="0xFFFFFFFF" AlphaWrite="Add" />
            </UIControl>
            <UIControl Name="item3" ClassName="CGUIStatic" LogicPos_x="69" LogicPos_y="79" Size_x="44" Size_y="44" Font="小白雅黑" TextRect_right="44" TextRect_bottom="44" TextColor="0xFFFFF2A4" ShadeColor="0xFF290404" TextWriteAlpha="yes" PicFileName="data\ui\common\l_icon.bmp" PicColor="0xFFFFFFFF" AlphaWrite="Add">
                <UIControl Name="icon" ClassName="CGUIStatic" LogicPos_x="4" LogicPos_y="4" Size_x="36" Size_y="36" Font="小白雅黑" FontHeight="15" TextRect_right="34" TextRect_bottom="36" TextColor="0xFFFFFFFF" ShadeColor="0xFF000000" TextWriteAlpha="yes" TextAlign="RightBottom" PicColor="0xFFFFFFFF" AlphaWrite="Add" />
            </UIControl>
            <UIControl Name="item4" ClassName="CGUIStatic" LogicPos_x="15" LogicPos_y="128" Size_x="44" Size_y="44" Font="小白雅黑" TextRect_right="44" TextRect_bottom="44" TextColor="0xFFFFF2A4" ShadeColor="0xFF290404" TextWriteAlpha="yes" PicFileName="data\ui\common\l_icon.bmp" PicColor="0xFFFFFFFF" AlphaWrite="Add">
                <UIControl Name="icon" ClassName="CGUIStatic" LogicPos_x="4" LogicPos_y="4" Size_x="36" Size_y="36" Font="小白雅黑" FontHeight="15" TextRect_right="34" TextRect_bottom="36" TextColor="0xFFFFFFFF" ShadeColor="0xFF000000" TextWriteAlpha="yes" TextAlign="RightBottom" PicColor="0xFFFFFFFF" AlphaWrite="Add" />
            </UIControl>
            <UIControl Name="item5" ClassName="CGUIStatic" LogicPos_x="69" LogicPos_y="128" Size_x="44" Size_y="44" Font="小白雅黑" TextRect_right="44" TextRect_bottom="44" TextColor="0xFFFFF2A4" ShadeColor="0xFF290404" TextWriteAlpha="yes" PicFileName="data\ui\common\l_icon.bmp" PicColor="0xFFFFFFFF" AlphaWrite="Add">
                <UIControl Name="icon" ClassName="CGUIStatic" LogicPos_x="4" LogicPos_y="4" Size_x="36" Size_y="36" Font="小白雅黑" FontHeight="15" TextRect_right="34" TextRect_bottom="36" TextColor="0xFFFFFFFF" ShadeColor="0xFF000000" TextWriteAlpha="yes" TextAlign="RightBottom" PicColor="0xFFFFFFFF" AlphaWrite="Add" />
            </UIControl>
        </UIControl>
        <UIControl Name="info" ClassName="CGUIPatch" MoveFather="yes" LogicPos_x="252" Size_x="128" Size_y="185" AlignControl="\desktop\guardwin" AlignType="InnerRight" Text="积分信息" Font="小白雅黑" FontHeight="20" FontWeight="800" TextRect_top="5" TextRect_right="128" TextRect_bottom="185" TextColor="0xFFFFF2A4" ShadeColor="0xFF290404" TextWriteAlpha="yes" TextAlign="CenterTop" PicColor="0xEEFFFFFF" AlphaWrite="Write" TopPicFileName="data\ui\pet\l-pet.bmp" TopPicRect_left="9" TopPicRect_right="18" TopPicRect_bottom="9" MidPicFileName="data\ui\pet\l-pet.bmp" MidPicRect_left="9" MidPicRect_top="9" MidPicRect_right="18" MidPicRect_bottom="18" DownPicFileName="data\ui\pet\l-pet.bmp" DownPicRect_left="9" DownPicRect_top="18" DownPicRect_right="18" DownPicRect_bottom="27" LeftPicFileName="data\ui\pet\l-pet.bmp" LeftPicRect_top="9" LeftPicRect_right="9" LeftPicRect_bottom="18" RightPicFileName="data\ui\pet\l-pet.bmp" RightPicRect_left="18" RightPicRect_top="9" RightPicRect_right="27" RightPicRect_bottom="18" LeftTopPicFileName="data\ui\pet\l-pet.bmp" LeftTopPicRect_right="9" LeftTopPicRect_bottom="9" RightTopPicFileName="data\ui\pet\l-pet.bmp" RightTopPicRect_left="18" RightTopPicRect_right="27" RightTopPicRect_bottom="9" LeftDownPicFileName="data\ui\pet\l-pet.bmp" LeftDownPicRect_top="18" LeftDownPicRect_right="9" LeftDownPicRect_bottom="27" RightDownPicFileName="data\ui\pet\l-pet.bmp" RightDownPicRect_left="18" RightDownPicRect_top="18" RightDownPicRect_right="27" RightDownPicRect_bottom="27">
            <UIControl Name="word4" ClassName="CGUIStatic" LogicPos_x="9" LogicPos_y="150" Size_x="110" Size_y="17" Text="死亡次数:" Font="小白雅黑" FontHeight="16" TextRect_right="100" TextRect_bottom="17" TextColor="0xFFFFF2A4" ShadeColor="0xFF290404" TextWriteAlpha="yes" PicColor="0xFFFFFF" AlphaWrite="Add">
                <UIControl Name="num" ClassName="CGUIStatic" LogicPos_x="65" Size_x="40" Size_y="17" Font="小白雅黑" FontHeight="16" TextRect_right="40" TextRect_bottom="17" TextColor="0xFFFFF2A4" ShadeColor="0xFF290404" TextWriteAlpha="yes" TextAlign="LeftCenter" PicColor="0xFFFFFF" AlphaWrite="Add" />
            </UIControl>
            <UIControl Name="word3" ClassName="CGUIStatic" LogicPos_x="9" LogicPos_y="121" Size_x="110" Size_y="17" Text="BOSS击杀:" Font="小白雅黑" FontHeight="16" TextRect_right="100" TextRect_bottom="17" TextColor="0xFFFFF2A4" ShadeColor="0xFF290404" TextWriteAlpha="yes" PicColor="0xFFFFFF" AlphaWrite="Add">
                <UIControl Name="num" ClassName="CGUIStatic" LogicPos_x="65" Size_x="40" Size_y="17" Font="小白雅黑" FontHeight="16" TextRect_right="40" TextRect_bottom="17" TextColor="0xFFFFF2A4" ShadeColor="0xFF290404" TextWriteAlpha="yes" TextAlign="LeftCenter" PicColor="0xFFFFFF" AlphaWrite="Add" />
            </UIControl>
            <UIControl Name="word2" ClassName="CGUIStatic" LogicPos_x="9" LogicPos_y="92" Size_x="110" Size_y="17" Text="防守波数:" Font="小白雅黑" FontHeight="16" TextRect_right="110" TextRect_bottom="17" TextColor="0xFFFFF2A4" ShadeColor="0xFF290404" TextWriteAlpha="yes" PicColor="0xFFFFFF" AlphaWrite="Add">
                <UIControl Name="num" ClassName="CGUIStatic" LogicPos_x="65" Size_x="40" Size_y="17" Font="小白雅黑" FontHeight="16" TextRect_right="40" TextRect_bottom="17" TextColor="0xFFFFF2A4" ShadeColor="0xFF290404" TextWriteAlpha="yes" TextAlign="LeftCenter" PicColor="0xFFFFFF" AlphaWrite="Add" />
            </UIControl>
            <UIControl Name="word1" ClassName="CGUIStatic" LogicPos_x="9" LogicPos_y="63" Size_x="110" Size_y="17" Text="持续时间:" Font="小白雅黑" FontHeight="16" TextRect_right="100" TextRect_bottom="17" TextColor="0xFFFFF2A4" ShadeColor="0xFF290404" TextWriteAlpha="yes" PicColor="0xFFFFFF" AlphaWrite="Add">
                <UIControl Name="num" ClassName="CGUIStatic" LogicPos_x="65" Size_x="40" Size_y="17" Font="小白雅黑" FontHeight="16" TextRect_right="40" TextRect_bottom="17" TextColor="0xFFFFF2A4" ShadeColor="0xFF290404" TextWriteAlpha="yes" TextAlign="LeftCenter" PicColor="0xFFFFFF" AlphaWrite="Add" />
            </UIControl>
            <UIControl Name="word0" ClassName="CGUIStatic" LogicPos_x="9" LogicPos_y="34" Size_x="110" Size_y="17" Text="金币数:" Font="小白雅黑" FontHeight="16" TextRect_right="100" TextRect_bottom="17" TextColor="0xFFFFF2A4" ShadeColor="0xFF290404" TextWriteAlpha="yes" PicColor="0xFFFFFF" AlphaWrite="Add">
                <UIControl Name="num" ClassName="CGUIStatic" LogicPos_x="45" Size_x="60" Size_y="17" Font="小白雅黑" FontHeight="16" TextRect_left="20" TextRect_right="60" TextRect_bottom="17" TextColor="0xFFFFF2A4" ShadeColor="0xFF290404" TextWriteAlpha="yes" TextAlign="LeftCenter" PicColor="0xFFFFFF" AlphaWrite="Add">
                    <UIControl Name="pic" ClassName="CGUIStatic" LogicPos_y="1" Size_x="18" Size_y="15" Font="小三楷体" TextRect_right="18" TextRect_bottom="15" TextColor="0xFFFFF2A4" ShadeColor="0xFF290404" PicFileName="data\ui\guard\goldcoin.bmp" PicColor="0xFFFFFFFF" />
                </UIControl>
            </UIControl>
        </UIControl>
        <UIControl Name="warehouse" ClassName="CGUIPatch" MoveFather="yes" Size_x="128" Size_y="185" AlignOffset_x="126" Text="仓库栏" Font="小白雅黑" FontHeight="20" FontWeight="800" TextRect_top="5" TextRect_right="128" TextRect_bottom="185" TextColor="0xFFFFF2A4" ShadeColor="0xFF290404" TextWriteAlpha="yes" TextAlign="CenterTop" PicColor="0xEEFFFFFF" AlphaWrite="Write" TopPicFileName="data\ui\pet\l-pet.bmp" TopPicRect_left="9" TopPicRect_right="18" TopPicRect_bottom="9" MidPicFileName="data\ui\pet\l-pet.bmp" MidPicRect_left="9" MidPicRect_top="9" MidPicRect_right="18" MidPicRect_bottom="18" DownPicFileName="data\ui\pet\l-pet.bmp" DownPicRect_left="9" DownPicRect_top="18" DownPicRect_right="18" DownPicRect_bottom="27" LeftPicFileName="data\ui\pet\l-pet.bmp" LeftPicRect_top="9" LeftPicRect_right="9" LeftPicRect_bottom="18" RightPicFileName="data\ui\pet\l-pet.bmp" RightPicRect_left="18" RightPicRect_top="9" RightPicRect_right="27" RightPicRect_bottom="18" LeftTopPicFileName="data\ui\pet\l-pet.bmp" LeftTopPicRect_right="9" LeftTopPicRect_bottom="9" RightTopPicFileName="data\ui\pet\l-pet.bmp" RightTopPicRect_left="18" RightTopPicRect_right="27" RightTopPicRect_bottom="9" LeftDownPicFileName="data\ui\pet\l-pet.bmp" LeftDownPicRect_top="18" LeftDownPicRect_right="9" LeftDownPicRect_bottom="27" RightDownPicFileName="data\ui\pet\l-pet.bmp" RightDownPicRect_left="18" RightDownPicRect_top="18" RightDownPicRect_right="27" RightDownPicRect_bottom="27">
            <UIControl Name="item5" ClassName="CGUIStatic" LogicPos_x="69" LogicPos_y="128" Size_x="44" Size_y="44" Font="小白雅黑" TextRect_right="44" TextRect_bottom="44" TextColor="0xFFFFF2A4" ShadeColor="0xFF290404" TextWriteAlpha="yes" PicFileName="data\ui\common\l_icon.bmp" PicColor="0xFFFFFFFF" AlphaWrite="Add">
                <UIControl Name="icon" ClassName="CGUIStatic" LogicPos_x="4" LogicPos_y="4" Size_x="36" Size_y="36" Font="小白雅黑" FontHeight="15" TextRect_right="34" TextRect_bottom="36" TextColor="0xFFFFFFFF" ShadeColor="0xFF000000" TextWriteAlpha="yes" TextAlign="RightBottom" PicColor="0xFFFFFFFF" AlphaWrite="Add" />
            </UIControl>
            <UIControl Name="item4" ClassName="CGUIStatic" LogicPos_x="15" LogicPos_y="128" Size_x="44" Size_y="44" Font="小白雅黑" TextRect_right="44" TextRect_bottom="44" TextColor="0xFFFFF2A4" ShadeColor="0xFF290404" TextWriteAlpha="yes" PicFileName="data\ui\common\l_icon.bmp" PicColor="0xFFFFFFFF" AlphaWrite="Add">
                <UIControl Name="icon" ClassName="CGUIStatic" LogicPos_x="4" LogicPos_y="4" Size_x="36" Size_y="36" Font="小白雅黑" FontHeight="15" TextRect_right="34" TextRect_bottom="36" TextColor="0xFFFFFFFF" ShadeColor="0xFF000000" TextWriteAlpha="yes" TextAlign="RightBottom" PicColor="0xFFFFFFFF" AlphaWrite="Add" />
            </UIControl>
            <UIControl Name="item3" ClassName="CGUIStatic" LogicPos_x="69" LogicPos_y="79" Size_x="44" Size_y="44" Font="小白雅黑" TextRect_right="44" TextRect_bottom="44" TextColor="0xFFFFF2A4" ShadeColor="0xFF290404" TextWriteAlpha="yes" PicFileName="data\ui\common\l_icon.bmp" PicColor="0xFFFFFFFF" AlphaWrite="Add">
                <UIControl Name="icon" ClassName="CGUIStatic" LogicPos_x="4" LogicPos_y="4" Size_x="36" Size_y="36" Font="小白雅黑" FontHeight="15" TextRect_right="34" TextRect_bottom="36" TextColor="0xFFFFFFFF" ShadeColor="0xFF000000" TextWriteAlpha="yes" TextAlign="RightBottom" PicColor="0xFFFFFFFF" AlphaWrite="Add" />
            </UIControl>
            <UIControl Name="item2" ClassName="CGUIStatic" LogicPos_x="15" LogicPos_y="79" Size_x="44" Size_y="44" Font="小白雅黑" TextRect_right="44" TextRect_bottom="44" TextColor="0xFFFFF2A4" ShadeColor="0xFF290404" TextWriteAlpha="yes" PicFileName="data\ui\common\l_icon.bmp" PicColor="0xFFFFFFFF" AlphaWrite="Add">
                <UIControl Name="icon" ClassName="CGUIStatic" LogicPos_x="4" LogicPos_y="4" Size_x="36" Size_y="36" Font="小白雅黑" FontHeight="15" TextRect_right="34" TextRect_bottom="36" TextColor="0xFFFFFFFF" ShadeColor="0xFF000000" TextWriteAlpha="yes" TextAlign="RightBottom" PicColor="0xFFFFFFFF" AlphaWrite="Add" />
            </UIControl>
            <UIControl Name="item1" ClassName="CGUIStatic" LogicPos_x="69" LogicPos_y="30" Size_x="44" Size_y="44" Font="小白雅黑" TextRect_right="44" TextRect_bottom="44" TextColor="0xFFFFF2A4" ShadeColor="0xFF290404" PicFileName="data\ui\common\l_icon.bmp" PicColor="0xFFFFFFFF" AlphaWrite="Add">
                <UIControl Name="icon" ClassName="CGUIStatic" LogicPos_x="4" LogicPos_y="4" Size_x="36" Size_y="36" Font="小白雅黑" FontHeight="15" TextRect_right="34" TextRect_bottom="36" TextColor="0xFFFFFFFF" ShadeColor="0xFF000000" TextWriteAlpha="yes" TextAlign="RightBottom" PicColor="0xFFFFFFFF" AlphaWrite="Add" />
            </UIControl>
            <UIControl Name="item0" ClassName="CGUIStatic" LogicPos_x="15" LogicPos_y="30" Size_x="44" Size_y="44" Font="小白雅黑" TextRect_right="44" TextRect_bottom="44" TextColor="0xFFFFF2A4" ShadeColor="0xFF290404" PicFileName="data\ui\common\l_icon.bmp" PicColor="0xFFFFFFFF" AlphaWrite="Add">
                <UIControl Name="icon" ClassName="CGUIStatic" LogicPos_x="4" LogicPos_y="4" Size_x="36" Size_y="36" Font="小白雅黑" FontHeight="15" TextRect_right="34" TextRect_bottom="36" TextColor="0xFFFFFFFF" ShadeColor="0xFF000000" TextWriteAlpha="yes" TextAlign="RightBottom" PicColor="0xFFFFFFFF" AlphaWrite="Add" />
            </UIControl>
        </UIControl>
    </UIControl>
</desktop>
