<?xml version="1.0" encoding="UTF-8" ?>
<desktop>
    <UIControl Name="npclistwin" ClassName="CGUIWindow" Movable="yes" CanMoveOutOfFather="yes" LogicPos_x="937" LogicPos_y="176" Size_x="199" Size_y="592" AlignControl="\desktop" AlignOffset_x="12" AlignOffset_y="10" PopupSound="window_popup">
        <UIControl Name="npclistpic" ClassName="CGUIPatch" MoveFather="yes" LogicPos_x="2" LogicPos_y="20" Size_x="197" Size_y="572" AlignControl="\desktop\npclistwin" Font="小白雅黑" TextRect_right="197" TextRect_bottom="572" TextColor="0xFFFFFFFF" ShadeColor="0xFF290404" TextAlign="CenterTop" PicColor="0xFFFFFFFF" AlphaWrite="Write" TopPicFileName="data\ui\compose\l-compose.bmp" TopPicRect_left="30" TopPicRect_right="60" TopPicRect_bottom="30" MidPicFileName="data\ui\compose\l-compose.bmp" MidPicRect_left="30" MidPicRect_top="30" MidPicRect_right="60" MidPicRect_bottom="60" DownPicFileName="data\ui\compose\l-compose.bmp" DownPicRect_left="30" DownPicRect_top="60" DownPicRect_right="60" DownPicRect_bottom="90" LeftPicFileName="data\ui\compose\l-compose.bmp" LeftPicRect_top="30" LeftPicRect_right="30" LeftPicRect_bottom="60" RightPicFileName="data\ui\compose\l-compose.bmp" RightPicRect_left="60" RightPicRect_top="30" RightPicRect_right="90" RightPicRect_bottom="60" LeftTopPicFileName="data\ui\compose\l-compose.bmp" LeftTopPicRect_right="30" LeftTopPicRect_bottom="30" RightTopPicFileName="data\ui\compose\l-compose.bmp" RightTopPicRect_left="60" RightTopPicRect_right="90" RightTopPicRect_bottom="30" LeftDownPicFileName="data\ui\compose\l-compose.bmp" LeftDownPicRect_top="60" LeftDownPicRect_right="30" LeftDownPicRect_bottom="90" RightDownPicFileName="data\ui\compose\l-compose.bmp" RightDownPicRect_left="60" RightDownPicRect_top="60" RightDownPicRect_right="90" RightDownPicRect_bottom="90">
            <UIControl Name="npctitle" ClassName="CGUIStatic" MoveFather="yes" CanMoveOutOfFather="yes" LogicPos_x="-1" LogicPos_y="-20" Size_x="198" Size_y="36" AlignControl="\desktop\npclistwin\npclistpic" Text="可接任务(距离/米)" Font="小白雅黑" FontHeight="20" TextRect_left="-4" TextRect_top="8" TextRect_right="201" TextRect_bottom="36" TextColor="0xFFFFF2A4" ShadeColor="0xFF290404" TextAlign="CenterTop" PicFileName="data\ui\mission\l-mission.bmp" PicRect_left="29" PicRect_right="204" PicRect_bottom="33" PicColor="0xFFFFFFFF" AlphaWrite="Add">
                <UIControl Name="closebutt" ClassName="CGUIButton" LogicPos_x="171" LogicPos_y="7" Size_x="20" Size_y="20" AlignControl="\desktop\npclistwin\npclistpic\npctitle" Font="小白雅黑" TextRect_right="100" TextRect_bottom="100" TextColor="0xFFFFF2A4" ShadeColor="0xFF290404" PicFileName="data\ui\common\l-common.bmp" PicRect_left="344" PicRect_top="102" PicRect_right="363" PicRect_bottom="120" PicColor="0xFFFFFFFF" PushPicFileName="data\ui\common\l-common.bmp" PushPicRect_left="382" PushPicRect_top="102" PushPicRect_right="401" PushPicRect_bottom="120" PushPicColor="0xFFFFFFFF" PushTextColor="0xFFFFF2A4" PushShadeColor="0xFF290404" MovePicFileName="data\ui\common\l-common.bmp" MovePicRect_left="363" MovePicRect_top="102" MovePicRect_right="382" MovePicRect_bottom="120" MovePicColor="0xFFFFFFFF" MoveTextColor="0xFFFFF2A4" MoveShadeColor="0xFF290404" DisablePicFileName="data\ui\common\l-common.bmp" DisablePicRect_left="344" DisablePicRect_top="102" DisablePicRect_right="363" DisablePicRect_bottom="120" DisablePicColor="0xFFFFFFFF" DisableTextColor="0xFFFFF2A4" DisableShadeColor="0xFF290404" TopColor="0xFF000000" BottomColor="0xFFAFAFAF" />
            </UIControl>
            <UIControl Name="pic" ClassName="CGUIPatch" LogicPos_x="9" LogicPos_y="412" Size_x="179" Size_y="121" Font="小白雅黑" TextRect_right="179" TextRect_bottom="121" TextColor="0xFFFFF2A4" ShadeColor="0xFF290404" PicColor="0xFFFFFFFF" TopPicFileName="data\ui\pet\l-pet.bmp" TopPicRect_left="9" TopPicRect_right="18" TopPicRect_bottom="9" MidPicFileName="data\ui\pet\l-pet.bmp" MidPicRect_left="9" MidPicRect_top="9" MidPicRect_right="18" MidPicRect_bottom="18" DownPicFileName="data\ui\pet\l-pet.bmp" DownPicRect_left="9" DownPicRect_top="18" DownPicRect_right="18" DownPicRect_bottom="27" LeftPicFileName="data\ui\pet\l-pet.bmp" LeftPicRect_top="9" LeftPicRect_right="9" LeftPicRect_bottom="18" RightPicFileName="data\ui\pet\l-pet.bmp" RightPicRect_left="18" RightPicRect_top="9" RightPicRect_right="27" RightPicRect_bottom="18" LeftTopPicFileName="data\ui\pet\l-pet.bmp" LeftTopPicRect_right="9" LeftTopPicRect_bottom="9" RightTopPicFileName="data\ui\pet\l-pet.bmp" RightTopPicRect_left="18" RightTopPicRect_right="27" RightTopPicRect_bottom="9" LeftDownPicFileName="data\ui\pet\l-pet.bmp" LeftDownPicRect_top="18" LeftDownPicRect_right="9" LeftDownPicRect_bottom="27" RightDownPicFileName="data\ui\pet\l-pet.bmp" RightDownPicRect_left="18" RightDownPicRect_top="18" RightDownPicRect_right="27" RightDownPicRect_bottom="27">
                <UIControl Name="word3" ClassName="CGUIStatic" LogicPos_x="53" LogicPos_y="59" Size_x="108" Size_y="18" Font="小白雅黑" FontHeight="18" TextRect_right="108" TextRect_bottom="18" TextColor="0xFFFFF7E0" ShadeColor="0xFF290404" PicColor="0xFFFFFF" />
                <UIControl Name="word4" ClassName="CGUIStatic" LogicPos_x="53" LogicPos_y="86" Size_x="108" Size_y="18" Font="小白雅黑" FontHeight="18" TextRect_right="108" TextRect_bottom="18" TextColor="0xFFFFF7E0" ShadeColor="0xFF290404" PicColor="0xFFFFFF" />
                <UIControl Name="opbutt1" ClassName="CGUIPushButton" LogicPos_x="125" LogicPos_y="12" Size_x="12" Size_y="12" AlignControl="\desktop\back\pic\picset\reveal\word30\choose3" Font="小白雅黑" TextRect_right="12" TextRect_bottom="12" TextColor="0xFFFFFFFF" ShadeColor="0xFF290404" PicFileName="data\ui\common\l-common.bmp" PicRect_left="356" PicRect_top="58" PicRect_right="368" PicRect_bottom="70" PicColor="0xFFFFFFFF" PushPicFileName="data\ui\common\l-common.bmp" PushPicRect_left="344" PushPicRect_top="58" PushPicRect_right="356" PushPicRect_bottom="70" PushPicColor="0xFFFFFFFF" PushTextColor="0xFF000000" PushShadeColor="0xFF290404" MovePicFileName="data\ui\common\l-common.bmp" MovePicRect_left="356" MovePicRect_top="58" MovePicRect_right="368" MovePicRect_bottom="70" MovePicColor="0xFFFFFFFF" MoveTextColor="0xFF000000" MoveShadeColor="0xFF290404" DisablePicFileName="data\ui\common\l-common.bmp" DisablePicRect_left="368" DisablePicRect_top="58" DisablePicRect_right="380" DisablePicRect_bottom="70" DisablePicColor="0xFFFFFFFF" DisableTextColor="0xFFFFF2A4" DisableShadeColor="0xFF290404" TopColor="0xFF000000" BottomColor="0xFFAFAFAF" />
                <UIControl Name="word1" ClassName="CGUIStatic" LogicPos_x="10" LogicPos_y="10" Size_x="101" Size_y="18" Text="过滤低等级任务" Font="小白雅黑" FontHeight="18" TextRect_right="101" TextRect_bottom="18" TextColor="0xFFFFF7E0" ShadeColor="0xFF290404" PicColor="0xFFFFFF" />
                <UIControl Name="word2" ClassName="CGUIStatic" LogicPos_x="10" LogicPos_y="32" Size_x="101" Size_y="18" Text="按类型过滤任务" Font="小白雅黑" FontHeight="18" TextRect_right="101" TextRect_bottom="18" TextColor="0xFFFFF7E0" ShadeColor="0xFF290404" PicColor="0xFFFFFF" />
                <UIControl Name="frm" ClassName="CGUIFrameMutex" LogicPos_x="7" LogicPos_y="57" Size_x="20" Size_y="46">
                    <UIControl Name="opbutt1" ClassName="CGUIPushButton" LogicPos_x="5" LogicPos_y="6" Size_x="12" Size_y="12" AlignControl="\desktop\back\pic\picset\reveal\word30\choose3" Font="小白雅黑" TextRect_right="12" TextRect_bottom="12" TextColor="0xFFFFFFFF" ShadeColor="0xFF290404" PicFileName="data\ui\common\l-common.bmp" PicRect_left="356" PicRect_top="58" PicRect_right="368" PicRect_bottom="70" PicColor="0xFFFFFFFF" PushPicFileName="data\ui\common\l-common.bmp" PushPicRect_left="344" PushPicRect_top="58" PushPicRect_right="356" PushPicRect_bottom="70" PushPicColor="0xFFFFFFFF" PushTextColor="0xFF000000" PushShadeColor="0xFF290404" MovePicFileName="data\ui\common\l-common.bmp" MovePicRect_left="356" MovePicRect_top="58" MovePicRect_right="368" MovePicRect_bottom="70" MovePicColor="0xFFFFFFFF" MoveTextColor="0xFF000000" MoveShadeColor="0xFF290404" DisablePicFileName="data\ui\common\l-common.bmp" DisablePicRect_left="368" DisablePicRect_top="58" DisablePicRect_right="380" DisablePicRect_bottom="70" DisablePicColor="0xFFFFFFFF" DisableTextColor="0xFFFFF2A4" DisableShadeColor="0xFF290404" TopColor="0xFF000000" BottomColor="0xFFAFAFAF" />
                    <UIControl Name="opbutt2" ClassName="CGUIPushButton" LogicPos_x="5" LogicPos_y="33" Size_x="12" Size_y="12" AlignControl="\desktop\back\pic\picset\reveal\word30\choose3" Font="小白雅黑" TextRect_right="12" TextRect_bottom="12" TextColor="0xFFFFFFFF" ShadeColor="0xFF290404" PicFileName="data\ui\common\l-common.bmp" PicRect_left="356" PicRect_top="58" PicRect_right="368" PicRect_bottom="70" PicColor="0xFFFFFFFF" PushPicFileName="data\ui\common\l-common.bmp" PushPicRect_left="344" PushPicRect_top="58" PushPicRect_right="356" PushPicRect_bottom="70" PushPicColor="0xFFFFFFFF" PushTextColor="0xFF000000" PushShadeColor="0xFF290404" MovePicFileName="data\ui\common\l-common.bmp" MovePicRect_left="356" MovePicRect_top="58" MovePicRect_right="368" MovePicRect_bottom="70" MovePicColor="0xFFFFFFFF" MoveTextColor="0xFF000000" MoveShadeColor="0xFF290404" DisablePicFileName="data\ui\common\l-common.bmp" DisablePicRect_left="368" DisablePicRect_top="58" DisablePicRect_right="380" DisablePicRect_bottom="70" DisablePicColor="0xFFFFFFFF" DisableTextColor="0xFFFFF2A4" DisableShadeColor="0xFF290404" TopColor="0xFF000000" BottomColor="0xFFAFAFAF" />
                </UIControl>
                <UIControl Name="word6" ClassName="CGUIStatic" LogicPos_x="30" LogicPos_y="86" Size_x="19" Size_y="19" Text="贰" Font="小白雅黑" FontHeight="18" TextRect_right="19" TextRect_bottom="19" TextColor="0xFFFFF7E0" ShadeColor="0xFF290404" PicColor="0xFFFFFF" />
                <UIControl Name="word5" ClassName="CGUIStatic" LogicPos_x="30" LogicPos_y="59" Size_x="19" Size_y="19" Text="壹" Font="小白雅黑" FontHeight="18" TextRect_right="19" TextRect_bottom="19" TextColor="0xFFFFF7E0" ShadeColor="0xFF290404" PicColor="0xFFFFFF" />
                <UIControl Name="opbutt2" ClassName="CGUIPushButton" LogicPos_x="125" LogicPos_y="35" Size_x="12" Size_y="12" AlignControl="\desktop\back\pic\picset\reveal\word30\choose3" Font="小白雅黑" TextRect_right="12" TextRect_bottom="12" TextColor="0xFFFFFFFF" ShadeColor="0xFF290404" PicFileName="data\ui\common\l-common.bmp" PicRect_left="356" PicRect_top="58" PicRect_right="368" PicRect_bottom="70" PicColor="0xFFFFFFFF" PushPicFileName="data\ui\common\l-common.bmp" PushPicRect_left="344" PushPicRect_top="58" PushPicRect_right="356" PushPicRect_bottom="70" PushPicColor="0xFFFFFFFF" PushTextColor="0xFF000000" PushShadeColor="0xFF290404" MovePicFileName="data\ui\common\l-common.bmp" MovePicRect_left="356" MovePicRect_top="58" MovePicRect_right="368" MovePicRect_bottom="70" MovePicColor="0xFFFFFFFF" MoveTextColor="0xFF000000" MoveShadeColor="0xFF290404" DisablePicFileName="data\ui\common\l-common.bmp" DisablePicRect_left="368" DisablePicRect_top="58" DisablePicRect_right="380" DisablePicRect_bottom="70" DisablePicColor="0xFFFFFFFF" DisableTextColor="0xFFFFF2A4" DisableShadeColor="0xFF290404" TopColor="0xFF000000" BottomColor="0xFFAFAFAF" />
            </UIControl>
            <UIControl Name="npclist" ClassName="CGUIListBox" LogicPos_x="5" LogicPos_y="13" Size_x="174" Size_y="397" AlignControl="\desktop\npclistwin\npclistpic" Font="小白雅黑" FontHeight="18" TextRect_right="164" TextRect_bottom="397" TextColor="0xFFFFF7E0" ShadeColor="0xFF290404" TextAlign="LeftCenter" PicFileName="data\ui\sys\l_diban-a.bmp" PicColor="0xFFFFFFFF" RowHeight="18" SelectStickPicFileName="data\ui\common\l_choose-l.bmp" SelectStickColor="0xFFFFFF" SelectStickActiveColor="0xFFFFFFFF" RowLineColor="0xFFFFFF" SelectTextColor="0xFFFFF7E0" PicSize_x="16" PicSize_y="16">
                <UIControl Name="nlscr" ClassName="CGUIScrollBar" CanMoveOutOfFather="yes" LogicPos_x="177" LogicPos_y="12" Size_x="11" Size_y="378" AlignControl="\desktop\npclistwin\npclistpic\npclist" AlignType="OuterRight" AlignOffset_x="3" AlignOffset_y="3" Font="隶书" TextRect_right="100" TextRect_bottom="100" TextColor="0xFFFFFFFF" ShadeColor="0xFF290404" PicFileName="data\ui\common\l-common.bmp" PicRect_left="305" PicRect_top="97" PicRect_right="338" PicRect_bottom="193" PicColor="0xFFFFFFFF" TotalValue="22" VisibleValue="22" TopPicFileName="data\ui\common\l-common.bmp" TopPicRect_left="327" TopPicRect_top="88" TopPicRect_right="336" TopPicRect_bottom="96" TopPicColor="0xFFFFFFFF" MidPicFileName="data\ui\common\l-common.bmp" MidPicRect_left="327" MidPicRect_top="96" MidPicRect_right="336" MidPicRect_bottom="97" MidPicColor="0xFFFFFFFF" DownPicFileName="data\ui\common\l-common.bmp" DownPicRect_left="327" DownPicRect_top="88" DownPicRect_right="336" DownPicRect_bottom="96" BelowPicColor="0xFFFFFFFF" TopColor="0xFF000000" BottomColor="0xFFAFAFAF">
                    <UIControl Name="nl_up" ClassName="CGUIButton" CanMoveOutOfFather="yes" LogicPos_y="-12" Size_x="11" Size_y="11" AlignControl="\desktop\ttalkwin\npclistpic\npclist\nlscr" AlignType="OuterTop" Font="隶书" TextRect_right="100" TextRect_bottom="100" TextColor="0xFFFFFFFF" ShadeColor="0xFF290404" PicFileName="data\ui\common\l-common.bmp" PicRect_left="344" PicRect_top="80" PicRect_right="355" PicRect_bottom="91" PicColor="0xFFFFFFFF" PushPicFileName="data\ui\common\l-common.bmp" PushPicRect_left="366" PushPicRect_top="80" PushPicRect_right="377" PushPicRect_bottom="91" PushPicColor="0xFFFFFFFF" PushTextColor="0xFF000000" PushShadeColor="0xFF290404" MovePicFileName="data\ui\common\l-common.bmp" MovePicRect_left="355" MovePicRect_top="80" MovePicRect_right="366" MovePicRect_bottom="91" MovePicColor="0xFFFFFFFF" MoveTextColor="0xFF000000" MoveShadeColor="0xFF290404" DisablePicFileName="data\ui\common\l-common.bmp" DisablePicRect_left="377" DisablePicRect_top="80" DisablePicRect_right="388" DisablePicRect_bottom="91" DisablePicColor="0xFFFFFFFF" DisableTextColor="0xFFFFF2A4" DisableShadeColor="0xFF290404" TopColor="0xFF000000" BottomColor="0xFFAFAFAF" />
                    <UIControl Name="nl_down" ClassName="CGUIButton" CanMoveOutOfFather="yes" LogicPos_y="378" Size_x="11" Size_y="11" AlignControl="\desktop\npclistwin\npclistpic\npclist\nlscr" AlignType="OuterBottom" Font="隶书" TextRect_right="100" TextRect_bottom="100" TextColor="0xFFFFFFFF" ShadeColor="0xFF290404" PicFileName="data\ui\common\l-common.bmp" PicRect_left="344" PicRect_top="91" PicRect_right="355" PicRect_bottom="102" PicColor="0xFFFFFFFF" PushPicFileName="data\ui\common\l-common.bmp" PushPicRect_left="366" PushPicRect_top="91" PushPicRect_right="377" PushPicRect_bottom="102" PushPicColor="0xFFFFFFFF" PushTextColor="0xFF000000" PushShadeColor="0xFF290404" MovePicFileName="data\ui\common\l-common.bmp" MovePicRect_left="355" MovePicRect_top="91" MovePicRect_right="366" MovePicRect_bottom="102" MovePicColor="0xFFFFFFFF" MoveTextColor="0xFF000000" MoveShadeColor="0xFF290404" DisablePicFileName="data\ui\common\l-common.bmp" DisablePicRect_left="377" DisablePicRect_top="91" DisablePicRect_right="388" DisablePicRect_bottom="102" DisablePicColor="0xFFFFFFFF" DisableTextColor="0xFFFFF2A4" DisableShadeColor="0xFF290404" TopColor="0xFF000000" BottomColor="0xFFAFAFAF" />
                </UIControl>
            </UIControl>
            <UIControl Name="butt" ClassName="CGUIButton" LogicPos_x="28" LogicPos_y="538" Size_x="136" Size_y="23" Text="手动配置任务过滤" Font="小白雅黑" FontHeight="20" TextRect_right="136" TextRect_bottom="23" TextColor="0xFFFFF7E0" ShadeColor="0xFF290404" TextAlign="Center" PicFileName="data\ui\sys\l-sys.bmp" PicRect_right="108" PicRect_bottom="22" PicColor="0xFFFFFFFF" PushPicFileName="data\ui\sys\l-sys.bmp" PushPicRect_top="44" PushPicRect_right="108" PushPicRect_bottom="66" PushPicColor="0xFFFFFFFF" PushTextColor="0xFFFFF7E0" PushShadeColor="0xFF290404" MovePicFileName="data\ui\sys\l-sys.bmp" MovePicRect_top="22" MovePicRect_right="108" MovePicRect_bottom="44" MovePicColor="0xFFFFFFFF" MoveTextColor="0xFFFFF7E0" MoveShadeColor="0xFF290404" DisablePicFileName="data\ui\sys\l-sys.bmp" DisablePicRect_top="66" DisablePicRect_right="108" DisablePicRect_bottom="88" DisablePicColor="0xFFFFFFFF" DisableTextColor="0xFFC0C0C0" DisableShadeColor="0xFF290404" TopColor="0xFF000000" BottomColor="0xFFAFAFAF" />
        </UIControl>
    </UIControl>
</desktop>
