<?xml version="1.0" encoding="UTF-8" standalone="yes"?>
<root>
	<Item TypeID="3303006" TableID="101" Num="2" BeginRate="0.04" RoleRate="0.02" ServerRate="0.01" NormalRate="0.12"/>
	<Item TypeID="3200707" TableID="102" Num="1" BeginRate="0.04" RoleRate="0.02" ServerRate="0.01" NormalRate="0.12"/>
	<Item TypeID="1350018" TableID="103" Num="3" BeginRate="0.04" RoleRate="0.02" ServerRate="0.01" NormalRate="0.12"/>
	<Item TypeID="3303313" TableID="104" Num="1" BeginRate="0.04" RoleRate="0.02" ServerRate="0.01" NormalRate="0.08"/>
	<Item TypeID="3303312" TableID="105" Num="1" BeginRate="0.04" RoleRate="0.02" ServerRate="0.01" NormalRate="0.08"/>
	<Item TypeID="1350002" TableID="106" Num="1" BeginRate="0.15" RoleRate="0.04" ServerRate="0.01" NormalRate="0.15"/>
	<Item TypeID="3303010" TableID="107" Num="1" BeginRate="0.15" RoleRate="0.04" ServerRate="0.01" NormalRate="0.08"/>
	<Item TypeID="3303012" TableID="108" Num="1" BeginRate="0.15" RoleRate="0.04" ServerRate="0.01" NormalRate="0.08"/>
	<Item TypeID="1350016" TableID="109" Num="2" BeginRate="0.15" RoleRate="0.04" ServerRate="0.01" NormalRate="0.08"/>
	<Item TypeID="1350017" TableID="110" Num="1" BeginRate="0.1" RoleRate="0.1" ServerRate="0.01" NormalRate="0.055"/>
	<Item TypeID="1350019" TableID="111" Num="1" BeginRate="0.05" RoleRate="0.3" ServerRate="0.1" NormalRate="0.02"/>
	<Item TypeID="3200727" TableID="112" Num="1" BeginRate="0.05" RoleRate="0.3" ServerRate="0.1" NormalRate="0.0125"/>
	<Item TypeID="4005203" TableID="113" Num="1" BeginRate="0" RoleRate="0.01" ServerRate="0.1" NormalRate="0.0025"/>
	<Item TypeID="8971001" TableID="114" Num="1" BeginRate="0" RoleRate="0.01" ServerRate="0.25" NormalRate="0"/>
	<Item TypeID="8971008" TableID="115" Num="1" BeginRate="0" RoleRate="0.01" ServerRate="0.25" NormalRate="0"/>
	<Item TypeID="8971013" TableID="116" Num="1" BeginRate="0" RoleRate="0.01" ServerRate="0.1" NormalRate="0"/>
	<Item TypeID="3303006" TableID="201" Num="2" BeginRate="0.04" RoleRate="0.02" ServerRate="0.01" NormalRate="0.12"/>
	<Item TypeID="3200707" TableID="202" Num="1" BeginRate="0.04" RoleRate="0.02" ServerRate="0.01" NormalRate="0.12"/>
	<Item TypeID="1350018" TableID="203" Num="3" BeginRate="0.04" RoleRate="0.02" ServerRate="0.01" NormalRate="0.12"/>
	<Item TypeID="3303313" TableID="204" Num="1" BeginRate="0.04" RoleRate="0.02" ServerRate="0.01" NormalRate="0.08"/>
	<Item TypeID="3303312" TableID="205" Num="1" BeginRate="0.04" RoleRate="0.02" ServerRate="0.01" NormalRate="0.08"/>
	<Item TypeID="1350002" TableID="206" Num="1" BeginRate="0.15" RoleRate="0.04" ServerRate="0.01" NormalRate="0.15"/>
	<Item TypeID="3303010" TableID="207" Num="1" BeginRate="0.15" RoleRate="0.04" ServerRate="0.01" NormalRate="0.08"/>
	<Item TypeID="3303012" TableID="208" Num="1" BeginRate="0.15" RoleRate="0.04" ServerRate="0.01" NormalRate="0.08"/>
	<Item TypeID="1350016" TableID="209" Num="2" BeginRate="0.15" RoleRate="0.04" ServerRate="0.01" NormalRate="0.08"/>
	<Item TypeID="1350017" TableID="210" Num="1" BeginRate="0.1" RoleRate="0.1" ServerRate="0.01" NormalRate="0.055"/>
	<Item TypeID="1350019" TableID="211" Num="1" BeginRate="0.05" RoleRate="0.3" ServerRate="0.1" NormalRate="0.02"/>
	<Item TypeID="3200727" TableID="212" Num="1" BeginRate="0.05" RoleRate="0.3" ServerRate="0.1" NormalRate="0.0125"/>
	<Item TypeID="4005203" TableID="213" Num="1" BeginRate="0" RoleRate="0.01" ServerRate="0.1" NormalRate="0.0025"/>
	<Item TypeID="8971001" TableID="214" Num="1" BeginRate="0" RoleRate="0.01" ServerRate="0.2" NormalRate="0"/>
	<Item TypeID="8971008" TableID="215" Num="1" BeginRate="0" RoleRate="0.01" ServerRate="0.2" NormalRate="0"/>
	<Item TypeID="8971013" TableID="216" Num="1" BeginRate="0" RoleRate="0.01" ServerRate="0.2" NormalRate="0"/>
	<Item TypeID="3303007" TableID="301" Num="1" BeginRate="0.2" RoleRate="0.2" ServerRate="0.02" NormalRate="0.13"/>
	<Item TypeID="3200707" TableID="302" Num="2" BeginRate="0.05" RoleRate="0.02" ServerRate="0.02" NormalRate="0.13"/>
	<Item TypeID="3303313" TableID="303" Num="1" BeginRate="0.05" RoleRate="0.02" ServerRate="0.02" NormalRate="0.1"/>
	<Item TypeID="3303312" TableID="304" Num="1" BeginRate="0.05" RoleRate="0.02" ServerRate="0.02" NormalRate="0.1"/>
	<Item TypeID="3303030" TableID="305" Num="2" BeginRate="0.2" RoleRate="0.02" ServerRate="0.02" NormalRate="0.1"/>
	<Item TypeID="3303010" TableID="306" Num="2" BeginRate="0.05" RoleRate="0.02" ServerRate="0.05" NormalRate="0.1"/>
	<Item TypeID="3303012" TableID="307" Num="2" BeginRate="0.05" RoleRate="0.02" ServerRate="0.05" NormalRate="0.1"/>
	<Item TypeID="1350017" TableID="308" Num="2" BeginRate="0.2" RoleRate="0.1" ServerRate="0.05" NormalRate="0.1"/>
	<Item TypeID="1350019" TableID="309" Num="1" BeginRate="0.05" RoleRate="0.2" ServerRate="0.05" NormalRate="0.1"/>
	<Item TypeID="3200727" TableID="310" Num="1" BeginRate="0.1" RoleRate="0.2" ServerRate="0.05" NormalRate="0.0325"/>
	<Item TypeID="4005203" TableID="311" Num="1" BeginRate="0" RoleRate="0.05" ServerRate="0.1" NormalRate="0.006"/>
	<Item TypeID="8971001" TableID="312" Num="1" BeginRate="0" RoleRate="0.05" ServerRate="0.2" NormalRate="0"/>
	<Item TypeID="8971017" TableID="313" Num="1" BeginRate="0" RoleRate="0.05" ServerRate="0.2" NormalRate="0"/>
	<Item TypeID="3303154" TableID="314" Num="1" BeginRate="0" RoleRate="0.01" ServerRate="0.05" NormalRate="0.0005"/>
	<Item TypeID="3303155" TableID="315" Num="1" BeginRate="0" RoleRate="0.01" ServerRate="0.05" NormalRate="0.0005"/>
	<Item TypeID="3303156" TableID="316" Num="1" BeginRate="0" RoleRate="0.01" ServerRate="0.05" NormalRate="0.0005"/>
	<Item TypeID="3303007" TableID="401" Num="1" BeginRate="0.2" RoleRate="0.2" ServerRate="0.02" NormalRate="0.13"/>
	<Item TypeID="3200707" TableID="402" Num="2" BeginRate="0.05" RoleRate="0.02" ServerRate="0.02" NormalRate="0.13"/>
	<Item TypeID="3303313" TableID="403" Num="1" BeginRate="0.05" RoleRate="0.02" ServerRate="0.02" NormalRate="0.1"/>
	<Item TypeID="3303312" TableID="404" Num="1" BeginRate="0.05" RoleRate="0.02" ServerRate="0.02" NormalRate="0.1"/>
	<Item TypeID="3303030" TableID="405" Num="2" BeginRate="0.2" RoleRate="0.02" ServerRate="0.02" NormalRate="0.1"/>
	<Item TypeID="3303010" TableID="406" Num="2" BeginRate="0.05" RoleRate="0.02" ServerRate="0.05" NormalRate="0.1"/>
	<Item TypeID="3303012" TableID="407" Num="2" BeginRate="0.05" RoleRate="0.02" ServerRate="0.05" NormalRate="0.1"/>
	<Item TypeID="1350017" TableID="408" Num="2" BeginRate="0.2" RoleRate="0.1" ServerRate="0.05" NormalRate="0.1"/>
	<Item TypeID="1350019" TableID="409" Num="1" BeginRate="0.05" RoleRate="0.2" ServerRate="0.05" NormalRate="0.1"/>
	<Item TypeID="3200727" TableID="410" Num="1" BeginRate="0.1" RoleRate="0.2" ServerRate="0.05" NormalRate="0.0325"/>
	<Item TypeID="4005203" TableID="411" Num="1" BeginRate="0" RoleRate="0.05" ServerRate="0.1" NormalRate="0.006"/>
	<Item TypeID="8971008" TableID="412" Num="1" BeginRate="0" RoleRate="0.05" ServerRate="0.2" NormalRate="0"/>
	<Item TypeID="8971017" TableID="413" Num="1" BeginRate="0" RoleRate="0.05" ServerRate="0.2" NormalRate="0"/>
	<Item TypeID="3303154" TableID="414" Num="1" BeginRate="0" RoleRate="0.01" ServerRate="0.05" NormalRate="0.0005"/>
	<Item TypeID="3303155" TableID="415" Num="1" BeginRate="0" RoleRate="0.01" ServerRate="0.05" NormalRate="0.0005"/>
	<Item TypeID="3303156" TableID="416" Num="1" BeginRate="0" RoleRate="0.01" ServerRate="0.05" NormalRate="0.0005"/>
	<Item TypeID="3303007" TableID="501" Num="1" BeginRate="0.2" RoleRate="0.2" ServerRate="0.02" NormalRate="0.13"/>
	<Item TypeID="3200707" TableID="502" Num="2" BeginRate="0.05" RoleRate="0.02" ServerRate="0.02" NormalRate="0.13"/>
	<Item TypeID="3303313" TableID="503" Num="1" BeginRate="0.05" RoleRate="0.02" ServerRate="0.02" NormalRate="0.1"/>
	<Item TypeID="3303312" TableID="504" Num="1" BeginRate="0.05" RoleRate="0.02" ServerRate="0.02" NormalRate="0.1"/>
	<Item TypeID="3303030" TableID="505" Num="2" BeginRate="0.2" RoleRate="0.02" ServerRate="0.02" NormalRate="0.1"/>
	<Item TypeID="3303010" TableID="506" Num="2" BeginRate="0.05" RoleRate="0.02" ServerRate="0.05" NormalRate="0.1"/>
	<Item TypeID="3303012" TableID="507" Num="2" BeginRate="0.05" RoleRate="0.02" ServerRate="0.05" NormalRate="0.1"/>
	<Item TypeID="1350017" TableID="508" Num="2" BeginRate="0.2" RoleRate="0.1" ServerRate="0.05" NormalRate="0.1"/>
	<Item TypeID="1350019" TableID="509" Num="1" BeginRate="0.05" RoleRate="0.2" ServerRate="0.05" NormalRate="0.1"/>
	<Item TypeID="3200727" TableID="510" Num="1" BeginRate="0.1" RoleRate="0.2" ServerRate="0.05" NormalRate="0.0325"/>
	<Item TypeID="4005203" TableID="511" Num="1" BeginRate="0" RoleRate="0.05" ServerRate="0.1" NormalRate="0.006"/>
	<Item TypeID="8971013" TableID="512" Num="1" BeginRate="0" RoleRate="0.05" ServerRate="0.2" NormalRate="0"/>
	<Item TypeID="8971017" TableID="513" Num="1" BeginRate="0" RoleRate="0.05" ServerRate="0.2" NormalRate="0"/>
	<Item TypeID="3303154" TableID="514" Num="1" BeginRate="0" RoleRate="0.01" ServerRate="0.05" NormalRate="0.0005"/>
	<Item TypeID="3303155" TableID="515" Num="1" BeginRate="0" RoleRate="0.01" ServerRate="0.05" NormalRate="0.0005"/>
	<Item TypeID="3303156" TableID="516" Num="1" BeginRate="0" RoleRate="0.01" ServerRate="0.05" NormalRate="0.0005"/>
	<Item TypeID="1352004" TableID="601" Num="1" BeginRate="0" RoleRate="0" ServerRate="0" NormalRate="0"/>
	<Item TypeID="4005316" TableID="602" Num="1" BeginRate="0" RoleRate="0.01" ServerRate="0.05" NormalRate="0.0001"/>
	<Item TypeID="1351208" TableID="603" Num="1" BeginRate="0" RoleRate="0.01" ServerRate="0.05" NormalRate="0.0002"/>
	<Item TypeID="4005314" TableID="604" Num="1" BeginRate="0" RoleRate="0.02" ServerRate="0.05" NormalRate="0.0002"/>
	<Item TypeID="3304007" TableID="605" Num="2" BeginRate="0" RoleRate="0.9" ServerRate="0.4" NormalRate="0.005"/>
	<Item TypeID="3304006" TableID="606" Num="2" BeginRate="0" RoleRate="0.02" ServerRate="0.45" NormalRate="0.01"/>
	<Item TypeID="3304005" TableID="607" Num="2" BeginRate="0" RoleRate="0" ServerRate="0" NormalRate="0.01"/>
	<Item TypeID="3304004" TableID="608" Num="2" BeginRate="0.09" RoleRate="0" ServerRate="0" NormalRate="0.015"/>
	<Item TypeID="2220401" TableID="609" Num="1" BeginRate="0" RoleRate="0" ServerRate="0" NormalRate="0.02"/>
	<Item TypeID="3304013" TableID="610" Num="1" BeginRate="0.9" RoleRate="0.04" ServerRate="0" NormalRate="0.02"/>
	<Item TypeID="3302101" TableID="611" Num="1" BeginRate="0" RoleRate="0" ServerRate="0" NormalRate="0.1"/>
	<Item TypeID="1352003" TableID="612" Num="1" BeginRate="0.01" RoleRate="0" ServerRate="0" NormalRate="0.1"/>
	<Item TypeID="1351203" TableID="613" Num="5" BeginRate="0" RoleRate="0" ServerRate="0" NormalRate="0.1195"/>
	<Item TypeID="1360117" TableID="614" Num="2" BeginRate="0" RoleRate="0" ServerRate="0" NormalRate="0.2"/>
	<Item TypeID="3303030" TableID="615" Num="4" BeginRate="0" RoleRate="0" ServerRate="0" NormalRate="0.2"/>
	<Item TypeID="3304001" TableID="616" Num="4" BeginRate="0" RoleRate="0" ServerRate="0" NormalRate="0.2"/>
	<Item TypeID="4005002" TableID="701" Num="1" BeginRate="0.002" RoleRate="0.002" ServerRate="0.3" NormalRate="0.002"/>
	<Item TypeID="1350412" TableID="702" Num="1" BeginRate="0" RoleRate="0" ServerRate="0" NormalRate="0"/>
	<Item TypeID="1350414" TableID="703" Num="1" BeginRate="0.001" RoleRate="0.001" ServerRate="0" NormalRate="0.001"/>
	<Item TypeID="8990001" TableID="704" Num="1" BeginRate="0.005" RoleRate="0.005" ServerRate="0.1" NormalRate="0.005"/>
	<Item TypeID="8990002" TableID="705" Num="1" BeginRate="0.005" RoleRate="0.005" ServerRate="0.1" NormalRate="0.005"/>
	<Item TypeID="8990003" TableID="706" Num="1" BeginRate="0.005" RoleRate="0.005" ServerRate="0.1" NormalRate="0.005"/>
	<Item TypeID="8990004" TableID="707" Num="1" BeginRate="0.005" RoleRate="0.005" ServerRate="0.1" NormalRate="0.005"/>
	<Item TypeID="1350409" TableID="708" Num="1" BeginRate="0.01" RoleRate="0.01" ServerRate="0" NormalRate="0.01"/>
	<Item TypeID="4005001" TableID="709" Num="1" BeginRate="0.002" RoleRate="0.002" ServerRate="0.3" NormalRate="0.002"/>
	<Item TypeID="1350408" TableID="710" Num="1" BeginRate="0.01" RoleRate="0.01" ServerRate="0" NormalRate="0.01"/>
	<Item TypeID="1350407" TableID="711" Num="1" BeginRate="0.015" RoleRate="0.015" ServerRate="0" NormalRate="0.015"/>
	<Item TypeID="1350406" TableID="712" Num="1" BeginRate="0.08" RoleRate="0.08" ServerRate="0" NormalRate="0.08"/>
	<Item TypeID="1350403" TableID="713" Num="1" BeginRate="0.13" RoleRate="0.13" ServerRate="0" NormalRate="0.13"/>
	<Item TypeID="1350402" TableID="714" Num="1" BeginRate="0.16" RoleRate="0.16" ServerRate="0" NormalRate="0.16"/>
	<Item TypeID="1350415" TableID="715" Num="2" BeginRate="0.33" RoleRate="0.33" ServerRate="0" NormalRate="0.33"/>
	<Item TypeID="1350401" TableID="716" Num="1" BeginRate="0.24" RoleRate="0.24" ServerRate="0" NormalRate="0.24"/>
	<Item TypeID="1340004" TableID="801" Num="1" BeginRate="0" RoleRate="0" ServerRate="0" NormalRate="0"/>
	<Item TypeID="1421009" TableID="802" Num="1" BeginRate="0.01" RoleRate="0.01" ServerRate="0.01" NormalRate="0.01"/>
	<Item TypeID="1421013" TableID="803" Num="1" BeginRate="0.01" RoleRate="0.01" ServerRate="0.01" NormalRate="0.01"/>
	<Item TypeID="1421017" TableID="804" Num="1" BeginRate="0.01" RoleRate="0.01" ServerRate="0.01" NormalRate="0.01"/>
	<Item TypeID="1421021" TableID="805" Num="1" BeginRate="0.01" RoleRate="0.01" ServerRate="0.01" NormalRate="0.01"/>
	<Item TypeID="1421033" TableID="806" Num="1" BeginRate="0.01" RoleRate="0.01" ServerRate="0.01" NormalRate="0.01"/>
	<Item TypeID="1421037" TableID="807" Num="1" BeginRate="0.01" RoleRate="0.01" ServerRate="0.01" NormalRate="0.01"/>
	<Item TypeID="3303007" TableID="808" Num="1" BeginRate="0.02" RoleRate="0.02" ServerRate="0.02" NormalRate="0.02"/>
	<Item TypeID="3303010" TableID="809" Num="1" BeginRate="0.07" RoleRate="0.07" ServerRate="0.07" NormalRate="0.07"/>
	<Item TypeID="3303012" TableID="810" Num="1" BeginRate="0.07" RoleRate="0.07" ServerRate="0.07" NormalRate="0.07"/>
	<Item TypeID="2005002" TableID="811" Num="1" BeginRate="0.13" RoleRate="0.13" ServerRate="0.13" NormalRate="0.13"/>
	<Item TypeID="2005012" TableID="812" Num="1" BeginRate="0.13" RoleRate="0.13" ServerRate="0.13" NormalRate="0.13"/>
	<Item TypeID="2005022" TableID="813" Num="1" BeginRate="0.13" RoleRate="0.13" ServerRate="0.13" NormalRate="0.13"/>
	<Item TypeID="2005032" TableID="814" Num="1" BeginRate="0.13" RoleRate="0.13" ServerRate="0.13" NormalRate="0.13"/>
	<Item TypeID="2005042" TableID="815" Num="1" BeginRate="0.13" RoleRate="0.13" ServerRate="0.13" NormalRate="0.13"/>
	<Item TypeID="2005052" TableID="816" Num="1" BeginRate="0.13" RoleRate="0.13" ServerRate="0.13" NormalRate="0.13"/>
	<Item TypeID="4000023" TableID="901" Num="1" BeginRate="0.001" RoleRate="0.01" ServerRate="0.04" NormalRate="0.001"/>
	<Item TypeID="8990201" TableID="902" Num="1" BeginRate="0.001" RoleRate="0.01" ServerRate="0.04" NormalRate="0.001"/>
	<Item TypeID="8990202" TableID="903" Num="1" BeginRate="0.005" RoleRate="0.02" ServerRate="0.04" NormalRate="0.005"/>
	<Item TypeID="8990001" TableID="904" Num="1" BeginRate="0.01" RoleRate="0.05" ServerRate="0.04" NormalRate="0.01"/>
	<Item TypeID="8990002" TableID="905" Num="1" BeginRate="0.01" RoleRate="0.05" ServerRate="0.04" NormalRate="0.01"/>
	<Item TypeID="8990003" TableID="906" Num="1" BeginRate="0.01" RoleRate="0.05" ServerRate="0.2" NormalRate="0.01"/>
	<Item TypeID="8990004" TableID="907" Num="1" BeginRate="0.01" RoleRate="0.05" ServerRate="0.2" NormalRate="0.01"/>
	<Item TypeID="3303151" TableID="908" Num="1" BeginRate="0.01" RoleRate="0.05" ServerRate="0.2" NormalRate="0.01"/>
	<Item TypeID="4700102" TableID="909" Num="1" BeginRate="0.01" RoleRate="0.05" ServerRate="0.2" NormalRate="0.01"/>
	<Item TypeID="1350415" TableID="910" Num="1" BeginRate="0.15" RoleRate="0.2" ServerRate="0" NormalRate="0.05"/>
	<Item TypeID="1360103" TableID="911" Num="1" BeginRate="0.15" RoleRate="0.2" ServerRate="0" NormalRate="0.05"/>
	<Item TypeID="4700101" TableID="912" Num="1" BeginRate="0.15" RoleRate="0" ServerRate="0" NormalRate="0.08"/>
	<Item TypeID="3303007" TableID="913" Num="1" BeginRate="0.1" RoleRate="0" ServerRate="0" NormalRate="0.1"/>
	<Item TypeID="3303010" TableID="914" Num="1" BeginRate="0.1" RoleRate="0" ServerRate="0" NormalRate="0.15"/>
	<Item TypeID="3303012" TableID="915" Num="1" BeginRate="0.1" RoleRate="0" ServerRate="0" NormalRate="0.15"/>
	<Item TypeID="2612601" TableID="916" Num="5" BeginRate="0.183" RoleRate="0.26" ServerRate="0" NormalRate="0.353"/>
	<Item TypeID="3303219" TableID="1001" Num="1" BeginRate="0" RoleRate="0" ServerRate="0" NormalRate="0"/>
	<Item TypeID="3303208" TableID="1002" Num="1" BeginRate="0.4" RoleRate="0.15" ServerRate="0" NormalRate="0.25"/>
	<Item TypeID="3303209" TableID="1003" Num="1" BeginRate="0.3" RoleRate="0.15" ServerRate="0" NormalRate="0.2"/>
	<Item TypeID="4005307" TableID="1004" Num="1" BeginRate="0" RoleRate="0.02" ServerRate="0.4" NormalRate="0"/>
	<Item TypeID="4005308" TableID="1005" Num="1" BeginRate="0" RoleRate="0.02" ServerRate="0.4" NormalRate="0"/>
	<Item TypeID="3303202" TableID="1006" Num="1" BeginRate="0.01" RoleRate="0.05" ServerRate="0.05" NormalRate="0"/>
	<Item TypeID="3303203" TableID="1007" Num="1" BeginRate="0" RoleRate="0" ServerRate="0.05" NormalRate="0"/>
	<Item TypeID="3303211" TableID="1008" Num="1" BeginRate="0.03" RoleRate="0.1" ServerRate="0" NormalRate="0.03"/>
	<Item TypeID="3303212" TableID="1009" Num="1" BeginRate="0.06" RoleRate="0.1" ServerRate="0" NormalRate="0.06"/>
	<Item TypeID="3303214" TableID="1010" Num="1" BeginRate="0" RoleRate="0" ServerRate="0" NormalRate="0.06"/>
	<Item TypeID="3303215" TableID="1011" Num="1" BeginRate="0" RoleRate="0.05" ServerRate="0" NormalRate="0.06"/>
	<Item TypeID="3303216" TableID="1012" Num="1" BeginRate="0" RoleRate="0.05" ServerRate="0" NormalRate="0.06"/>
	<Item TypeID="3303217" TableID="1013" Num="1" BeginRate="0" RoleRate="0.05" ServerRate="0" NormalRate="0.06"/>
	<Item TypeID="3303218" TableID="1014" Num="1" BeginRate="0" RoleRate="0.1" ServerRate="0" NormalRate="0.06"/>
	<Item TypeID="3200710" TableID="1015" Num="1" BeginRate="0.12" RoleRate="0.1" ServerRate="0.05" NormalRate="0.1"/>
	<Item TypeID="3200711" TableID="1016" Num="1" BeginRate="0.08" RoleRate="0.06" ServerRate="0.05" NormalRate="0.06"/>
	<Item TypeID="4005308" TableID="1101" Num="1" BeginRate="0" RoleRate="0" ServerRate="0" NormalRate="0"/>
	<Item TypeID="4005308" TableID="1102" Num="1" BeginRate="0.4" RoleRate="0.15" ServerRate="0" NormalRate="0.25"/>
	<Item TypeID="4005308" TableID="1103" Num="1" BeginRate="0.3" RoleRate="0.15" ServerRate="0" NormalRate="0.2"/>
	<Item TypeID="4005308" TableID="1104" Num="1" BeginRate="0" RoleRate="0.02" ServerRate="0.4" NormalRate="0"/>
	<Item TypeID="4005308" TableID="1105" Num="1" BeginRate="0" RoleRate="0.02" ServerRate="0.4" NormalRate="0"/>
	<Item TypeID="4005308" TableID="1106" Num="1" BeginRate="0.01" RoleRate="0.05" ServerRate="0.05" NormalRate="0"/>
	<Item TypeID="4005308" TableID="1107" Num="1" BeginRate="0" RoleRate="0" ServerRate="0.05" NormalRate="0"/>
	<Item TypeID="4005308" TableID="1108" Num="1" BeginRate="0.03" RoleRate="0.1" ServerRate="0" NormalRate="0.03"/>
	<Item TypeID="4005308" TableID="1109" Num="1" BeginRate="0.06" RoleRate="0.1" ServerRate="0" NormalRate="0.06"/>
	<Item TypeID="4005308" TableID="1110" Num="1" BeginRate="0" RoleRate="0" ServerRate="0" NormalRate="0.06"/>
	<Item TypeID="4005308" TableID="1111" Num="1" BeginRate="0" RoleRate="0.05" ServerRate="0" NormalRate="0.06"/>
	<Item TypeID="4005308" TableID="1112" Num="1" BeginRate="0" RoleRate="0.05" ServerRate="0" NormalRate="0.06"/>
	<Item TypeID="4005308" TableID="1113" Num="1" BeginRate="0" RoleRate="0.05" ServerRate="0" NormalRate="0.06"/>
	<Item TypeID="4005308" TableID="1114" Num="1" BeginRate="0" RoleRate="0.1" ServerRate="0" NormalRate="0.06"/>
	<Item TypeID="4005308" TableID="1115" Num="1" BeginRate="0.12" RoleRate="0.1" ServerRate="0.05" NormalRate="0.1"/>
	<Item TypeID="4005308" TableID="1116" Num="1" BeginRate="0.08" RoleRate="0.06" ServerRate="0.05" NormalRate="0.06"/>
	<Item TypeID="3200709" TableID="1201" Num="1" BeginRate="0.06" RoleRate="0" ServerRate="0" NormalRate="0.06"/>
	<Item TypeID="3200710" TableID="1202" Num="1" BeginRate="0.06" RoleRate="0.25" ServerRate="0" NormalRate="0.06"/>
	<Item TypeID="3200711" TableID="1203" Num="1" BeginRate="0.045" RoleRate="0.25" ServerRate="0.3" NormalRate="0.045"/>
	<Item TypeID="3200715" TableID="1204" Num="1" BeginRate="0.02" RoleRate="0" ServerRate="0" NormalRate="0.02"/>
	<Item TypeID="3303709" TableID="1205" Num="1" BeginRate="0.07" RoleRate="0" ServerRate="0" NormalRate="0.1"/>
	<Item TypeID="3303710" TableID="1206" Num="1" BeginRate="0.07" RoleRate="0" ServerRate="0" NormalRate="0.1"/>
	<Item TypeID="3303711" TableID="1207" Num="1" BeginRate="0.12" RoleRate="0.05" ServerRate="0" NormalRate="0.18"/>
	<Item TypeID="4005104" TableID="1208" Num="1" BeginRate="0" RoleRate="0.05" ServerRate="0.5" NormalRate="0"/>
	<Item TypeID="2000026" TableID="1209" Num="1" BeginRate="0.075" RoleRate="0.1" ServerRate="0.05" NormalRate="0.035"/>
	<Item TypeID="2000027" TableID="1210" Num="1" BeginRate="0.075" RoleRate="0.1" ServerRate="0.05" NormalRate="0.035"/>
	<Item TypeID="2000028" TableID="1211" Num="1" BeginRate="0.075" RoleRate="0.1" ServerRate="0.05" NormalRate="0.035"/>
	<Item TypeID="2000226" TableID="1212" Num="1" BeginRate="0.075" RoleRate="0.1" ServerRate="0.05" NormalRate="0.035"/>
	<Item TypeID="2000227" TableID="1213" Num="1" BeginRate="0.08" RoleRate="0" ServerRate="0" NormalRate="0.04"/>
	<Item TypeID="2000228" TableID="1214" Num="1" BeginRate="0.08" RoleRate="0" ServerRate="0" NormalRate="0.04"/>
	<Item TypeID="3303707" TableID="1215" Num="1" BeginRate="0.06" RoleRate="0" ServerRate="0" NormalRate="0.18"/>
	<Item TypeID="3303708" TableID="1216" Num="1" BeginRate="0.035" RoleRate="0" ServerRate="0" NormalRate="0.035"/>
	<Item TypeID="3200709" TableID="1301" Num="1" BeginRate="0.01" RoleRate="0.01" ServerRate="0.01" NormalRate="0.01"/>
	<Item TypeID="1140001" TableID="1302" Num="1" BeginRate="0.01" RoleRate="0.01" ServerRate="0.01" NormalRate="0.01"/>
	<Item TypeID="1421007" TableID="1303" Num="1" BeginRate="0.02" RoleRate="0.02" ServerRate="0.02" NormalRate="0.02"/>
	<Item TypeID="1421011" TableID="1304" Num="1" BeginRate="0.02" RoleRate="0.02" ServerRate="0.02" NormalRate="0.02"/>
	<Item TypeID="1421015" TableID="1305" Num="1" BeginRate="0.02" RoleRate="0.02" ServerRate="0.02" NormalRate="0.02"/>
	<Item TypeID="1421019" TableID="1306" Num="1" BeginRate="0.02" RoleRate="0.02" ServerRate="0.02" NormalRate="0.02"/>
	<Item TypeID="1421031" TableID="1307" Num="1" BeginRate="0.02" RoleRate="0.02" ServerRate="0.02" NormalRate="0.02"/>
	<Item TypeID="1421035" TableID="1308" Num="1" BeginRate="0.02" RoleRate="0.02" ServerRate="0.02" NormalRate="0.02"/>
	<Item TypeID="1413001" TableID="1309" Num="1" BeginRate="0.05" RoleRate="0.05" ServerRate="0.05" NormalRate="0.05"/>
	<Item TypeID="2611501" TableID="1310" Num="1" BeginRate="0.08" RoleRate="0.08" ServerRate="0.08" NormalRate="0.08"/>
	<Item TypeID="1350001" TableID="1311" Num="1" BeginRate="0.08" RoleRate="0.08" ServerRate="0.08" NormalRate="0.08"/>
	<Item TypeID="2420003" TableID="1312" Num="1" BeginRate="0.1" RoleRate="0.1" ServerRate="0.1" NormalRate="0.1"/>
	<Item TypeID="1211002" TableID="1313" Num="1" BeginRate="0.1" RoleRate="0.1" ServerRate="0.1" NormalRate="0.1"/>
	<Item TypeID="1212002" TableID="1314" Num="1" BeginRate="0.1" RoleRate="0.1" ServerRate="0.1" NormalRate="0.1"/>
	<Item TypeID="4700001" TableID="1315" Num="1" BeginRate="0.175" RoleRate="0.175" ServerRate="0.175" NormalRate="0.175"/>
	<Item TypeID="4500021" TableID="1316" Num="1" BeginRate="0.175" RoleRate="0.175" ServerRate="0.175" NormalRate="0.175"/>
	<Item TypeID="1410129" TableID="1401" Num="1" BeginRate="0" RoleRate="0" ServerRate="0.3" NormalRate="0"/>
	<Item TypeID="1410128" TableID="1402" Num="1" BeginRate="0" RoleRate="0" ServerRate="0.2" NormalRate="0"/>
	<Item TypeID="2000005" TableID="1403" Num="1" BeginRate="0.02" RoleRate="0.12" ServerRate="0.1" NormalRate="0.004"/>
	<Item TypeID="2000010" TableID="1404" Num="1" BeginRate="0.02" RoleRate="0.12" ServerRate="0.1" NormalRate="0.004"/>
	<Item TypeID="2000015" TableID="1405" Num="1" BeginRate="0.02" RoleRate="0.12" ServerRate="0.1" NormalRate="0.004"/>
	<Item TypeID="2000020" TableID="1406" Num="1" BeginRate="0.02" RoleRate="0.12" ServerRate="0.1" NormalRate="0.004"/>
	<Item TypeID="2000025" TableID="1407" Num="1" BeginRate="0.02" RoleRate="0.12" ServerRate="0.1" NormalRate="0.004"/>
	<Item TypeID="2000004" TableID="1408" Num="1" BeginRate="0.14" RoleRate="0.06" ServerRate="0" NormalRate="0.036"/>
	<Item TypeID="2000009" TableID="1409" Num="1" BeginRate="0.14" RoleRate="0.06" ServerRate="0" NormalRate="0.036"/>
	<Item TypeID="2000014" TableID="1410" Num="1" BeginRate="0.14" RoleRate="0.06" ServerRate="0" NormalRate="0.036"/>
	<Item TypeID="2000019" TableID="1411" Num="1" BeginRate="0.14" RoleRate="0.06" ServerRate="0" NormalRate="0.036"/>
	<Item TypeID="2000024" TableID="1412" Num="1" BeginRate="0.14" RoleRate="0.06" ServerRate="0" NormalRate="0.036"/>
	<Item TypeID="2005201" TableID="1413" Num="1" BeginRate="0.05" RoleRate="0.05" ServerRate="0" NormalRate="0.05"/>
	<Item TypeID="2005301" TableID="1414" Num="1" BeginRate="0.05" RoleRate="0.05" ServerRate="0" NormalRate="0.05"/>
	<Item TypeID="4500025" TableID="1415" Num="1" BeginRate="0.05" RoleRate="0" ServerRate="0" NormalRate="0.35"/>
	<Item TypeID="1351106" TableID="1416" Num="1" BeginRate="0.05" RoleRate="0" ServerRate="0" NormalRate="0.35"/>
	<Item TypeID="1410128" TableID="1501" Num="1" BeginRate="0" RoleRate="0" ServerRate="0.3" NormalRate="0"/>
	<Item TypeID="1410130" TableID="1502" Num="1" BeginRate="0" RoleRate="0" ServerRate="0.2" NormalRate="0"/>
	<Item TypeID="2000901" TableID="1503" Num="1" BeginRate="0.04" RoleRate="0.12" ServerRate="0.1" NormalRate="0.002"/>
	<Item TypeID="2000902" TableID="1504" Num="1" BeginRate="0.04" RoleRate="0.12" ServerRate="0.1" NormalRate="0.002"/>
	<Item TypeID="2000903" TableID="1505" Num="1" BeginRate="0.04" RoleRate="0.12" ServerRate="0.1" NormalRate="0.002"/>
	<Item TypeID="2000904" TableID="1506" Num="1" BeginRate="0.04" RoleRate="0.12" ServerRate="0.1" NormalRate="0.002"/>
	<Item TypeID="2000905" TableID="1507" Num="1" BeginRate="0.04" RoleRate="0.12" ServerRate="0.1" NormalRate="0.002"/>
	<Item TypeID="2000005" TableID="1508" Num="1" BeginRate="0.12" RoleRate="0.08" ServerRate="0" NormalRate="0.06"/>
	<Item TypeID="2000010" TableID="1509" Num="1" BeginRate="0.12" RoleRate="0.08" ServerRate="0" NormalRate="0.06"/>
	<Item TypeID="2000015" TableID="1510" Num="1" BeginRate="0.12" RoleRate="0.08" ServerRate="0" NormalRate="0.06"/>
	<Item TypeID="2000020" TableID="1511" Num="1" BeginRate="0.12" RoleRate="0.08" ServerRate="0" NormalRate="0.06"/>
	<Item TypeID="2000025" TableID="1512" Num="1" BeginRate="0.12" RoleRate="0.08" ServerRate="0" NormalRate="0.06"/>
	<Item TypeID="2005201" TableID="1513" Num="1" BeginRate="0.05" RoleRate="0" ServerRate="0" NormalRate="0.1"/>
	<Item TypeID="2005301" TableID="1514" Num="1" BeginRate="0.05" RoleRate="0" ServerRate="0" NormalRate="0.1"/>
	<Item TypeID="4500025" TableID="1515" Num="1" BeginRate="0.05" RoleRate="0" ServerRate="0" NormalRate="0.245"/>
	<Item TypeID="1351106" TableID="1516" Num="1" BeginRate="0.05" RoleRate="0" ServerRate="0" NormalRate="0.245"/>
	<Item TypeID="1410135" TableID="1601" Num="1" BeginRate="0" RoleRate="0" ServerRate="0.3" NormalRate="0"/>
	<Item TypeID="1410134" TableID="1602" Num="1" BeginRate="0" RoleRate="0" ServerRate="0.2" NormalRate="0"/>
	<Item TypeID="2000205" TableID="1603" Num="1" BeginRate="0.02" RoleRate="0.12" ServerRate="0.1" NormalRate="0.004"/>
	<Item TypeID="2000210" TableID="1604" Num="1" BeginRate="0.02" RoleRate="0.12" ServerRate="0.1" NormalRate="0.004"/>
	<Item TypeID="2000215" TableID="1605" Num="1" BeginRate="0.02" RoleRate="0.12" ServerRate="0.1" NormalRate="0.004"/>
	<Item TypeID="2000220" TableID="1606" Num="1" BeginRate="0.02" RoleRate="0.12" ServerRate="0.1" NormalRate="0.004"/>
	<Item TypeID="2000225" TableID="1607" Num="1" BeginRate="0.02" RoleRate="0.12" ServerRate="0.1" NormalRate="0.004"/>
	<Item TypeID="2000204" TableID="1608" Num="1" BeginRate="0.14" RoleRate="0.06" ServerRate="0" NormalRate="0.036"/>
	<Item TypeID="2000209" TableID="1609" Num="1" BeginRate="0.14" RoleRate="0.06" ServerRate="0" NormalRate="0.036"/>
	<Item TypeID="2000214" TableID="1610" Num="1" BeginRate="0.14" RoleRate="0.06" ServerRate="0" NormalRate="0.036"/>
	<Item TypeID="2000219" TableID="1611" Num="1" BeginRate="0.14" RoleRate="0.06" ServerRate="0" NormalRate="0.036"/>
	<Item TypeID="2000224" TableID="1612" Num="1" BeginRate="0.14" RoleRate="0.06" ServerRate="0" NormalRate="0.036"/>
	<Item TypeID="2005201" TableID="1613" Num="1" BeginRate="0.05" RoleRate="0.05" ServerRate="0" NormalRate="0.05"/>
	<Item TypeID="2005301" TableID="1614" Num="1" BeginRate="0.05" RoleRate="0.05" ServerRate="0" NormalRate="0.05"/>
	<Item TypeID="4500025" TableID="1615" Num="1" BeginRate="0.05" RoleRate="0" ServerRate="0" NormalRate="0.35"/>
	<Item TypeID="1351106" TableID="1616" Num="1" BeginRate="0.05" RoleRate="0" ServerRate="0" NormalRate="0.35"/>
	<Item TypeID="1410134" TableID="1701" Num="1" BeginRate="0" RoleRate="0" ServerRate="0.3" NormalRate="0"/>
	<Item TypeID="1410136" TableID="1702" Num="1" BeginRate="0" RoleRate="0" ServerRate="0.2" NormalRate="0"/>
	<Item TypeID="2000906" TableID="1703" Num="1" BeginRate="0.04" RoleRate="0.12" ServerRate="0.1" NormalRate="0.002"/>
	<Item TypeID="2000907" TableID="1704" Num="1" BeginRate="0.04" RoleRate="0.12" ServerRate="0.1" NormalRate="0.002"/>
	<Item TypeID="2000908" TableID="1705" Num="1" BeginRate="0.04" RoleRate="0.12" ServerRate="0.1" NormalRate="0.002"/>
	<Item TypeID="2000909" TableID="1706" Num="1" BeginRate="0.04" RoleRate="0.12" ServerRate="0.1" NormalRate="0.002"/>
	<Item TypeID="2000910" TableID="1707" Num="1" BeginRate="0.04" RoleRate="0.12" ServerRate="0.1" NormalRate="0.002"/>
	<Item TypeID="2000205" TableID="1708" Num="1" BeginRate="0.12" RoleRate="0.08" ServerRate="0" NormalRate="0.06"/>
	<Item TypeID="2000210" TableID="1709" Num="1" BeginRate="0.12" RoleRate="0.08" ServerRate="0" NormalRate="0.06"/>
	<Item TypeID="2000215" TableID="1710" Num="1" BeginRate="0.12" RoleRate="0.08" ServerRate="0" NormalRate="0.06"/>
	<Item TypeID="2000220" TableID="1711" Num="1" BeginRate="0.12" RoleRate="0.08" ServerRate="0" NormalRate="0.06"/>
	<Item TypeID="2000225" TableID="1712" Num="1" BeginRate="0.12" RoleRate="0.08" ServerRate="0" NormalRate="0.06"/>
	<Item TypeID="2005201" TableID="1713" Num="1" BeginRate="0.05" RoleRate="0" ServerRate="0" NormalRate="0.1"/>
	<Item TypeID="2005301" TableID="1714" Num="1" BeginRate="0.05" RoleRate="0" ServerRate="0" NormalRate="0.1"/>
	<Item TypeID="4500025" TableID="1715" Num="1" BeginRate="0.05" RoleRate="0" ServerRate="0" NormalRate="0.245"/>
	<Item TypeID="1351106" TableID="1716" Num="1" BeginRate="0.05" RoleRate="0" ServerRate="0" NormalRate="0.245"/>
	<Item TypeID="3304145" TableID="1801" Num="1" BeginRate="0" RoleRate="0.02" ServerRate="0.4" NormalRate="0"/>
	<Item TypeID="3304146" TableID="1802" Num="1" BeginRate="0.14" RoleRate="0.1" ServerRate="0" NormalRate="0.1"/>
	<Item TypeID="3304147" TableID="1803" Num="1" BeginRate="0.14" RoleRate="0.1" ServerRate="0" NormalRate="0.1"/>
	<Item TypeID="3304148" TableID="1804" Num="1" BeginRate="0.09" RoleRate="0.1" ServerRate="0" NormalRate="0.05"/>
	<Item TypeID="3304153" TableID="1805" Num="1" BeginRate="0.09" RoleRate="0.1" ServerRate="0" NormalRate="0.05"/>
	<Item TypeID="3304154" TableID="1806" Num="1" BeginRate="0.05" RoleRate="0.1" ServerRate="0" NormalRate="0.1"/>
	<Item TypeID="3304152" TableID="1807" Num="1" BeginRate="0.05" RoleRate="0.1" ServerRate="0" NormalRate="0.05"/>
	<Item TypeID="4005317" TableID="1808" Num="1" BeginRate="0" RoleRate="0.02" ServerRate="0.2" NormalRate="0"/>
	<Item TypeID="2005201" TableID="1809" Num="1" BeginRate="0.03" RoleRate="0" ServerRate="0.1" NormalRate="0.1"/>
	<Item TypeID="2005301" TableID="1810" Num="1" BeginRate="0.03" RoleRate="0" ServerRate="0.1" NormalRate="0.05"/>
	<Item TypeID="4500024" TableID="1811" Num="1" BeginRate="0.05" RoleRate="0" ServerRate="0" NormalRate="0.05"/>
	<Item TypeID="8990001" TableID="1812" Num="1" BeginRate="0" RoleRate="0.12" ServerRate="0.1" NormalRate="0"/>
	<Item TypeID="8990002" TableID="1813" Num="1" BeginRate="0" RoleRate="0.12" ServerRate="0.1" NormalRate="0"/>
	<Item TypeID="8990003" TableID="1814" Num="1" BeginRate="0" RoleRate="0.06" ServerRate="0" NormalRate="0"/>
	<Item TypeID="8990004" TableID="1815" Num="1" BeginRate="0" RoleRate="0.06" ServerRate="0" NormalRate="0"/>
	<Item TypeID="1350415" TableID="1816" Num="1" BeginRate="0.33" RoleRate="0" ServerRate="0" NormalRate="0.35"/>
	<Item TypeID="3303325" TableID="1901" Num="1" BeginRate="0" RoleRate="0" ServerRate="0.25" NormalRate="0.0001"/>
	<Item TypeID="3303327" TableID="1902" Num="1" BeginRate="0" RoleRate="0" ServerRate="0.25" NormalRate="0.0001"/>
	<Item TypeID="3301066" TableID="1903" Num="1" BeginRate="0" RoleRate="0.4" ServerRate="0" NormalRate="0.0002"/>
	<Item TypeID="1352013" TableID="1904" Num="1" BeginRate="0.2" RoleRate="0" ServerRate="0" NormalRate="0.1094"/>
	<Item TypeID="3301067" TableID="1905" Num="1" BeginRate="0" RoleRate="0.4" ServerRate="0" NormalRate="0.0002"/>
	<Item TypeID="1340009" TableID="1906" Num="1" BeginRate="0" RoleRate="0" ServerRate="0" NormalRate="0.01"/>
	<Item TypeID="3300105" TableID="1907" Num="1" BeginRate="0" RoleRate="0.1" ServerRate="0" NormalRate="0.01"/>
	<Item TypeID="1320023" TableID="1908" Num="1" BeginRate="0" RoleRate="0.1" ServerRate="0" NormalRate="0.01"/>
	<Item TypeID="3200738" TableID="1909" Num="3" BeginRate="0.3" RoleRate="0" ServerRate="0" NormalRate="0.03"/>
	<Item TypeID="3200734" TableID="1910" Num="3" BeginRate="0.3" RoleRate="0" ServerRate="0" NormalRate="0.03"/>
	<Item TypeID="3303034" TableID="1911" Num="1" BeginRate="0" RoleRate="0" ServerRate="0" NormalRate="0.05"/>
	<Item TypeID="3300102" TableID="1912" Num="10" BeginRate="0" RoleRate="0" ServerRate="0" NormalRate="0.075"/>
	<Item TypeID="3300103" TableID="1913" Num="10" BeginRate="0" RoleRate="0" ServerRate="0" NormalRate="0.075"/>
	<Item TypeID="1350022" TableID="1914" Num="1" BeginRate="0" RoleRate="0" ServerRate="0" NormalRate="0.2"/>
	<Item TypeID="1320011" TableID="1915" Num="1" BeginRate="0" RoleRate="0" ServerRate="0.5" NormalRate="0.2"/>
	<Item TypeID="3200464" TableID="1916" Num="5" BeginRate="0.2" RoleRate="0" ServerRate="0" NormalRate="0.2"/>
	<Item TypeID="8907401" TableID="2001" Num="1" BeginRate="0" RoleRate="0.1" ServerRate="0.1" NormalRate="0"/>
	<Item TypeID="8907402" TableID="2002" Num="1" BeginRate="0" RoleRate="0.1" ServerRate="0.1" NormalRate="0"/>
	<Item TypeID="8907403" TableID="2003" Num="1" BeginRate="0" RoleRate="0.1" ServerRate="0.1" NormalRate="0"/>
	<Item TypeID="8907404" TableID="2004" Num="1" BeginRate="0" RoleRate="0.1" ServerRate="0.1" NormalRate="0"/>
	<Item TypeID="8907405" TableID="2005" Num="1" BeginRate="0" RoleRate="0.1" ServerRate="0.1" NormalRate="0"/>
	<Item TypeID="8907406" TableID="2006" Num="1" BeginRate="0" RoleRate="0.1" ServerRate="0.1" NormalRate="0"/>
	<Item TypeID="8907407" TableID="2007" Num="1" BeginRate="0" RoleRate="0.1" ServerRate="0.1" NormalRate="0"/>
	<Item TypeID="8907408" TableID="2008" Num="1" BeginRate="0" RoleRate="0.1" ServerRate="0.1" NormalRate="0"/>
	<Item TypeID="8907409" TableID="2009" Num="1" BeginRate="0" RoleRate="0.1" ServerRate="0.1" NormalRate="0"/>
	<Item TypeID="8907410" TableID="2010" Num="1" BeginRate="0" RoleRate="0.1" ServerRate="0.1" NormalRate="0"/>
	<Item TypeID="6000000" TableID="2011" Num="1" BeginRate="0" RoleRate="0" ServerRate="0" NormalRate="0.02"/>
	<Item TypeID="6000001" TableID="2012" Num="1" BeginRate="0" RoleRate="0" ServerRate="0" NormalRate="0.01"/>
	<Item TypeID="6000002" TableID="2013" Num="1" BeginRate="0" RoleRate="0" ServerRate="0" NormalRate="0.005"/>
	<Item TypeID="6000003" TableID="2014" Num="1" BeginRate="0.4" RoleRate="0" ServerRate="0" NormalRate="0.5"/>
	<Item TypeID="6000007" TableID="2015" Num="1" BeginRate="0.4" RoleRate="0" ServerRate="0" NormalRate="0.265"/>
	<Item TypeID="6000008" TableID="2016" Num="1" BeginRate="0.2" RoleRate="0" ServerRate="0" NormalRate="0.2"/>	
</root>